[
  {
    "ns": 0,
    "title": "Pomeranian (dog)",
    "pageid": 170595,
    "size": 26236,
    "wordcount": 2772,
    "snippet": "The <span class=\"searchmatch\">Pomeranian</span> (often known as a Pom) is a breed of <span class=\"searchmatch\">dog</span> of the Spitz type that is named for the Pomerania region in north-west Poland and north-east Germany",
    "timestamp": "2018-10-29T13:49:58Z"
  },
  {
    "ns": 0,
    "title": "Poodle",
    "pageid": 515115,
    "size": 62561,
    "wordcount": 6279,
    "snippet": "The poodle is a group of formal <span class=\"searchmatch\">dog</span> breeds, the Standard Poodle, Miniature Poodle and Toy Poodle. The origin of the breed is still discussed, with a prominent",
    "timestamp": "2018-10-16T17:35:23Z"
  },
  {
    "ns": 0,
    "title": "List of most popular dog breeds",
    "pageid": 9387389,
    "size": 13475,
    "wordcount": 411,
    "snippet": "This article lists the most popular <span class=\"searchmatch\">dog</span> breeds by registrations. Note: registrations shown are not the same as annual registrations, or as living individuals",
    "timestamp": "2018-10-21T17:07:46Z"
  },
  {
    "ns": 0,
    "title": "Keeshond",
    "pageid": 17274,
    "size": 18785,
    "wordcount": 2437,
    "snippet": "Gro\u00dfspitz, Mittelspitz, and Kleinspitz or <span class=\"searchmatch\">Pomeranian</span>. The Keeshond was previously known as the Dutch Barge <span class=\"searchmatch\">Dog</span>, as it was frequently seen on the barges",
    "timestamp": "2018-10-27T22:39:01Z"
  },
  {
    "ns": 0,
    "title": "Lap dog",
    "pageid": 790060,
    "size": 11715,
    "wordcount": 1442,
    "snippet": "have a double coat and tend to be a friendly, one-person <span class=\"searchmatch\">dog</span>.[citation needed] The <span class=\"searchmatch\">Pomeranian</span> is named after the Pomerania region in Central Europe, split",
    "timestamp": "2018-10-10T22:41:30Z"
  },
  {
    "ns": 0,
    "title": "Boo (dog)",
    "pageid": 36687534,
    "size": 4574,
    "wordcount": 452,
    "snippet": "September 6, 2017), another <span class=\"searchmatch\">Pomeranian</span>. Boo belongs to a San Francisco-based Facebook employee who created a Facebook page for the <span class=\"searchmatch\">dog</span> with the statement &quot;My",
    "timestamp": "2018-10-27T21:11:12Z"
  },
  {
    "ns": 0,
    "title": "German Spitz",
    "pageid": 1561942,
    "size": 8578,
    "wordcount": 839,
    "snippet": "curled over the back. Although the Kleinspitz and the <span class=\"searchmatch\">Pomeranian</span> look similar, they are not the same <span class=\"searchmatch\">dog</span>. German spitzes, like all spitzes, have many physical",
    "timestamp": "2018-10-17T16:50:40Z"
  },
  {
    "ns": 0,
    "title": "Japanese Spitz",
    "pageid": 2449337,
    "size": 13803,
    "wordcount": 1511,
    "snippet": "due to it being similar appearance to the white <span class=\"searchmatch\">Pomeranian</span> <span class=\"searchmatch\">dog</span>, American Eskimo <span class=\"searchmatch\">Dog</span> and Samoyed <span class=\"searchmatch\">Dog</span>. While they are a relatively new breed, they are",
    "timestamp": "2018-10-17T16:55:09Z"
  },
  {
    "ns": 0,
    "title": "Indian Spitz",
    "pageid": 4209306,
    "size": 4705,
    "wordcount": 547,
    "snippet": "The Indian Spitz is a spitz-type <span class=\"searchmatch\">dog</span> breed belonging to the Utility <span class=\"searchmatch\">Dog</span> group. It is very similar to the German Spitz in appearance but is roughly 1.5-2",
    "timestamp": "2018-05-19T13:20:29Z"
  },
  {
    "ns": 0,
    "title": "Spitz",
    "pageid": 740355,
    "size": 11000,
    "wordcount": 842,
    "snippet": "lap dogs. This trend is most evident in the tiny <span class=\"searchmatch\">Pomeranian</span>, which was originally a much larger <span class=\"searchmatch\">dog</span> closer to the size of a Keeshond before being bred",
    "timestamp": "2018-10-01T06:12:00Z"
  },
  {
    "ns": 0,
    "title": "Companion dog",
    "pageid": 1005823,
    "size": 5820,
    "wordcount": 586,
    "snippet": "Poodle Miniature Shar Pei Miniature Schnauzer Mixed-breed <span class=\"searchmatch\">dog</span> Papillon Pekingese Phal\u00e8ne <span class=\"searchmatch\">Pomeranian</span> Pug Shetland Sheepdog (Sheltie) Pembroke Welsh Corgi Shih",
    "timestamp": "2018-10-10T16:15:11Z"
  },
  {
    "ns": 0,
    "title": "Pomeranian",
    "pageid": 2697938,
    "size": 1809,
    "wordcount": 185,
    "snippet": "spoken by the <span class=\"searchmatch\">Pomeranians</span> since the High Middle Ages <span class=\"searchmatch\">Pomeranian</span> <span class=\"searchmatch\">dog</span>, a Spitz toy <span class=\"searchmatch\">dog</span> breed <span class=\"searchmatch\">Pomeranian</span> Coarsewool sheep (also <span class=\"searchmatch\">Pomeranian</span> sheep, Pommernschaf)",
    "timestamp": "2018-10-18T13:23:38Z"
  },
  {
    "ns": 0,
    "title": "Toy group",
    "pageid": 1515697,
    "size": 16244,
    "wordcount": 777,
    "snippet": "to classify a defined collection of <span class=\"searchmatch\">dog</span> breeds. Toy Group does not necessarily refer to one particular type of <span class=\"searchmatch\">dog</span>. Most major English-language kennel",
    "timestamp": "2018-08-23T16:16:22Z"
  },
  {
    "ns": 0,
    "title": "American Eskimo Dog",
    "pageid": 174751,
    "size": 11618,
    "wordcount": 1392,
    "snippet": "The American Eskimo <span class=\"searchmatch\">Dog</span> is a breed of companion <span class=\"searchmatch\">dog</span>, originating in Germany. The American Eskimo is a member of the Spitz family. The breed's progenitors",
    "timestamp": "2018-10-15T12:33:42Z"
  },
  {
    "ns": 0,
    "title": "Laika (dog breed)",
    "pageid": 7721179,
    "size": 5349,
    "wordcount": 547,
    "snippet": "Spitz and Japanese Spitz. Types of German Spitz American Eskimo <span class=\"searchmatch\">Dog</span> Keeshond <span class=\"searchmatch\">Pomeranian</span> (<span class=\"searchmatch\">dog</span>) Related breeds Finnish Spitz Indian Spitz Japanese Spitz Laika",
    "timestamp": "2018-07-08T01:24:05Z"
  },
  {
    "ns": 0,
    "title": "German Spitz Klein",
    "pageid": 4827493,
    "size": 3570,
    "wordcount": 352,
    "snippet": "portal Dogs portal Germany portal German Spitz American Eskimo <span class=\"searchmatch\">Dog</span> Keeshond <span class=\"searchmatch\">Pomeranian</span> Japanese Spitz German Spitz World, a UK-based website for owners",
    "timestamp": "2018-10-17T16:51:55Z"
  },
  {
    "ns": 0,
    "title": "Old German herding dogs",
    "pageid": 39034194,
    "size": 11550,
    "wordcount": 1053,
    "snippet": "extinct in the course of time. The German: pommerscher H\u00fctehund ('<span class=\"searchmatch\">Pomeranian</span> sheep-<span class=\"searchmatch\">dog</span>') and the German: H\u00fctespitz ('herding spitz') were also counted among",
    "timestamp": "2018-08-21T21:46:04Z"
  },
  {
    "ns": 0,
    "title": "Merle (dog coat)",
    "pageid": 1401179,
    "size": 18356,
    "wordcount": 1932,
    "snippet": "Bully, American Pit Bull Terrier, Chihuahua, <span class=\"searchmatch\">Pomeranian</span>, American Cocker Spaniel, and Catahoula Leopard <span class=\"searchmatch\">Dog</span>. In Dachshunds the merle marking is known as",
    "timestamp": "2018-05-01T05:47:50Z"
  },
  {
    "ns": 0,
    "title": "List of fictional dogs in live-action television",
    "pageid": 52975252,
    "size": 16398,
    "wordcount": 121,
    "snippet": "&quot;'Neighbours' pet <span class=\"searchmatch\">dog</span> Audrey loses cancer battle&quot;. Digital Spy. Retrieved 7 January 2014. Morrow, Laurie Bogart. The Giant Book of <span class=\"searchmatch\">Dog</span> Names. Simon and",
    "timestamp": "2018-09-13T21:37:10Z"
  },
  {
    "ns": 0,
    "title": "Toy dog",
    "pageid": 731386,
    "size": 19073,
    "wordcount": 1905,
    "snippet": "Toy <span class=\"searchmatch\">dog</span> traditionally refers to a very small <span class=\"searchmatch\">dog</span> or a grouping of small and very small breeds of <span class=\"searchmatch\">dog</span>. A toy <span class=\"searchmatch\">dog</span> may be of any of various <span class=\"searchmatch\">dog</span> types. Types",
    "timestamp": "2018-09-27T14:02:22Z"
  },
  {
    "ns": 0,
    "title": "Poodle crossbreed",
    "pageid": 1179868,
    "size": 7904,
    "wordcount": 842,
    "snippet": "and poodle Pomapoo - <span class=\"searchmatch\">Pomeranian</span> and poodle Poogle \u2013 beagle and poodle Schnoodle \u2013 schnauzer and poodle Sheepadoodle \u2013 sheep <span class=\"searchmatch\">dog</span> and poodle Shih-poo \u2013",
    "timestamp": "2018-10-14T14:40:21Z"
  },
  {
    "ns": 0,
    "title": "Pomerania",
    "pageid": 24261,
    "size": 33676,
    "wordcount": 3160,
    "snippet": "Kashubian-Pomeranian Association Pomerania State Museum <span class=\"searchmatch\">Pomeranian</span> (<span class=\"searchmatch\">dog</span>) Pomerode <span class=\"searchmatch\">Pomeranian</span> (disambiguation) Der Name Pommern (po more) ist slawischer",
    "timestamp": "2018-08-18T10:45:15Z"
  },
  {
    "ns": 0,
    "title": "Chester Drescher",
    "pageid": 1238367,
    "size": 2114,
    "wordcount": 199,
    "snippet": "Chester Drescher (1981\u20132000) was a performing <span class=\"searchmatch\">dog</span> and Fran Drescher's <span class=\"searchmatch\">Pomeranian</span>. He played C.C. Babcock's <span class=\"searchmatch\">dog</span> on The Nanny, who seemed to like nanny Fran",
    "timestamp": "2016-10-28T13:26:21Z"
  },
  {
    "ns": 0,
    "title": "Miniature Schnauzer",
    "pageid": 375411,
    "size": 24658,
    "wordcount": 2457,
    "snippet": "The Miniature Schnauzer is a breed of small <span class=\"searchmatch\">dog</span> of the Schnauzer type that originated in Germany in the mid-to-late 19th century. Miniature Schnauzers",
    "timestamp": "2018-10-17T12:37:41Z"
  },
  {
    "ns": 0,
    "title": "Schnauzer",
    "pageid": 889014,
    "size": 20150,
    "wordcount": 2320,
    "snippet": "which share common ancestry with spitz-type breeds American Eskimo <span class=\"searchmatch\">Dog</span>, <span class=\"searchmatch\">Pomeranian</span>, Volpino Italiano, Schipperke, Papillon, as well Griffon Bruxellois",
    "timestamp": "2018-10-19T16:53:19Z"
  },
  {
    "ns": 0,
    "title": "Bullenbeisser",
    "pageid": 3808877,
    "size": 2469,
    "wordcount": 253,
    "snippet": "The Bullenbeisser, also known as the German Bulldog, was a breed of <span class=\"searchmatch\">dog</span> known for its strength and agility. The breed was closely related to the B\u00e4renbeisser",
    "timestamp": "2018-10-29T13:57:21Z"
  },
  {
    "ns": 0,
    "title": "Herding dog",
    "pageid": 514072,
    "size": 14352,
    "wordcount": 1418,
    "snippet": "A herding <span class=\"searchmatch\">dog</span>, also known as a stock <span class=\"searchmatch\">dog</span> or working <span class=\"searchmatch\">dog</span>, is a type of pastoral <span class=\"searchmatch\">dog</span> that either has been trained in herding or belongs to breeds developed",
    "timestamp": "2018-08-22T11:53:56Z"
  },
  {
    "ns": 0,
    "title": "Tracheal collapse",
    "pageid": 4547560,
    "size": 4379,
    "wordcount": 466,
    "snippet": "Tracheal collapse is most commonly found in small <span class=\"searchmatch\">dog</span> breeds, including the Chihuahua, <span class=\"searchmatch\">Pomeranian</span>, Toy Poodle, Shih Tzu, Lhasa Apso, Maltese, Pug, and",
    "timestamp": "2017-04-13T00:53:14Z"
  },
  {
    "ns": 0,
    "title": "German Spitz Mittel",
    "pageid": 10236647,
    "size": 3551,
    "wordcount": 309,
    "snippet": "German Spitz Mittel is a breed, of the German spitz type. It is a companion <span class=\"searchmatch\">dog</span> originating in Germany. German Spitz Mittel originated in Germany sometime",
    "timestamp": "2018-10-17T16:52:50Z"
  },
  {
    "ns": 0,
    "title": "List of Best in Show winners of Crufts",
    "pageid": 25603919,
    "size": 37822,
    "wordcount": 1722,
    "snippet": "was Ch. The Sable Mite, a <span class=\"searchmatch\">Pomeranian</span>. According to Crufts: The Official History the first winner of that award was the first <span class=\"searchmatch\">dog</span> to be considered the &quot;best&quot;",
    "timestamp": "2018-09-05T19:12:03Z"
  },
  {
    "ns": 0,
    "title": "Hanover Hound",
    "pageid": 3168775,
    "size": 2555,
    "wordcount": 220,
    "snippet": "The Hanover Hound is a breed of <span class=\"searchmatch\">dog</span> sometimes referred to as a Hanoverian Hound. It is a hunting and tracking <span class=\"searchmatch\">dog</span> descended from bloodhounds of medieval",
    "timestamp": "2018-10-17T20:59:11Z"
  },
  {
    "ns": 0,
    "title": "Pudelpointer",
    "pageid": 54184,
    "size": 5176,
    "wordcount": 563,
    "snippet": "The Pudelpointer is a versatile hunting <span class=\"searchmatch\">dog</span> breed from Germany. It is a pointing breed that came from a cross between the German hunting poodle (pudel)",
    "timestamp": "2018-10-17T21:58:34Z"
  },
  {
    "ns": 0,
    "title": "Affenpinscher",
    "pageid": 273885,
    "size": 11877,
    "wordcount": 1071,
    "snippet": "also known as the Monkey Terrier, is a terrier-like toy Pinscher breed of <span class=\"searchmatch\">dog</span>. The breed is German in origin and dates back to the seventeenth century",
    "timestamp": "2018-10-17T23:19:34Z"
  },
  {
    "ns": 0,
    "title": "Landseer dog",
    "pageid": 1379724,
    "size": 5147,
    "wordcount": 516,
    "snippet": "The Landseer is a <span class=\"searchmatch\">dog</span> breed. The breed is not recognized by all kennel clubs[citation needed]. It is not to be confused with a white and black Newfoundland",
    "timestamp": "2018-10-17T12:49:16Z"
  },
  {
    "ns": 0,
    "title": "Stichelhaar",
    "pageid": 26604195,
    "size": 2403,
    "wordcount": 162,
    "snippet": "German Roughhaired Pointer (Deutsch Stichelhaar) is a versatile hunting <span class=\"searchmatch\">dog</span> that originated in Frankfurt, Germany. The breed was developed in the early",
    "timestamp": "2018-10-17T21:55:16Z"
  },
  {
    "ns": 0,
    "title": "Westphalian Dachsbracke",
    "pageid": 19405868,
    "size": 5502,
    "wordcount": 675,
    "snippet": "Dachsbracke (FCI No. 100) is a small, short-legged scenthound, a breed of <span class=\"searchmatch\">dog</span> originating in Westphalia, a region of Germany. The Westphalian Dachsbracke",
    "timestamp": "2018-10-17T20:58:10Z"
  },
  {
    "ns": 0,
    "title": "Mieczys\u0142aw M\u0142ynarski",
    "pageid": 14690822,
    "size": 5133,
    "wordcount": 320,
    "snippet": "Wa\u0142brzych (assistant)2009 G\u00f3rnik Wa\u0142brzych2009\u20132012 Nowe Miasto / KS Dark <span class=\"searchmatch\">Dog</span> G\u00f3rnik Wa\u0142brzych2016\u20132017 Prakto Polonia \u015awidnica Career highlights and awards",
    "timestamp": "2018-10-24T00:52:04Z"
  },
  {
    "ns": 0,
    "title": "Hovawart",
    "pageid": 2072982,
    "size": 7449,
    "wordcount": 782,
    "snippet": "The Hovawart is a medium to large size German <span class=\"searchmatch\">dog</span> breed. The name of the breed means &quot;an estate guard <span class=\"searchmatch\">dog</span>&quot;, which is the original use for the breed. The",
    "timestamp": "2018-10-17T12:48:13Z"
  },
  {
    "ns": 0,
    "title": "Old German Shepherd Dog",
    "pageid": 19620332,
    "size": 3494,
    "wordcount": 311,
    "snippet": "German Shepherd <span class=\"searchmatch\">Dog</span> (German: Altdeutscher Sch\u00e4ferhund) is a controversial name for the long-haired variation of the German Shepherd <span class=\"searchmatch\">Dog</span> (German: Langstockhaariger",
    "timestamp": "2018-10-24T20:39:22Z"
  },
  {
    "ns": 0,
    "title": "Miniature Pinscher",
    "pageid": 952060,
    "size": 11975,
    "wordcount": 1183,
    "snippet": "The Miniature Pinscher (Zwergpinscher or Min Pin) is a small breed of <span class=\"searchmatch\">dog</span> originating from Germany. The breed's earliest ancestors may have included the",
    "timestamp": "2018-10-17T12:36:27Z"
  },
  {
    "ns": 0,
    "title": "Wolfdog",
    "pageid": 505721,
    "size": 38889,
    "wordcount": 4518,
    "snippet": "wolf mated with a <span class=\"searchmatch\">dog</span> identified in the language of the day as a &quot;<span class=\"searchmatch\">Pomeranian</span>&quot;, although it may have differed from the modern <span class=\"searchmatch\">Pomeranian</span> breed. The union",
    "timestamp": "2018-10-21T02:00:10Z"
  },
  {
    "ns": 0,
    "title": "Pumi dog",
    "pageid": 2651850,
    "size": 23406,
    "wordcount": 2683,
    "snippet": "(in Hungarian, the plural form is pumik) is a medium-small breed of sheep <span class=\"searchmatch\">dog</span> from Hungary. They are versatile stock dogs equally adept at gathering, driving",
    "timestamp": "2018-10-16T21:35:45Z"
  },
  {
    "ns": 0,
    "title": "Great Dane",
    "pageid": 83416,
    "size": 36335,
    "wordcount": 3596,
    "snippet": "The Great Dane is a German breed of domestic <span class=\"searchmatch\">dog</span> known for its giant size. The German name of the breed is Deutsche Dogge, or German Mastiff. The French",
    "timestamp": "2018-10-22T08:06:55Z"
  },
  {
    "ns": 0,
    "title": "Bavarian Mountain Hound",
    "pageid": 3095466,
    "size": 4830,
    "wordcount": 598,
    "snippet": "Mountain Hound (German = &quot;Bayerischer Gebirgsschwei\u00dfhund&quot;) is a breed of <span class=\"searchmatch\">dog</span> from Germany. As a scent hound, it has been used in Germany since the early",
    "timestamp": "2018-10-17T20:58:49Z"
  },
  {
    "ns": 0,
    "title": "List of dog crossbreeds",
    "pageid": 14418001,
    "size": 12459,
    "wordcount": 246,
    "snippet": "This is a list of common <span class=\"searchmatch\">dog</span> crossbreeds. Originating as crossbreeds, now sustained independently of the parent breeds. These are dogs created deliberately",
    "timestamp": "2018-10-21T17:08:02Z"
  },
  {
    "ns": 0,
    "title": "Eurasier",
    "pageid": 2791594,
    "size": 8418,
    "wordcount": 888,
    "snippet": "The Eurasier, or Eurasian <span class=\"searchmatch\">dog</span>, is a breed of <span class=\"searchmatch\">dog</span> of the spitz type that originated in Germany. It is widely known as a wonderful companion that maintains",
    "timestamp": "2018-10-24T21:41:10Z"
  },
  {
    "ns": 0,
    "title": "Saarloos wolfdog",
    "pageid": 441452,
    "size": 5646,
    "wordcount": 578,
    "snippet": "Saarloos wolfhound (Dutch: Saarlooswolfhond) is an established breed of <span class=\"searchmatch\">dog</span> originating from wolfdog hybrid crosses. In 1935, Dutch breeder Leendert",
    "timestamp": "2018-10-22T03:00:30Z"
  },
  {
    "ns": 0,
    "title": "German Hound",
    "pageid": 22127733,
    "size": 8246,
    "wordcount": 1000,
    "snippet": "The German Hound (Deutsche Bracke) (FCI No. 299) is a breed of <span class=\"searchmatch\">dog</span> originating in Westphalia, a region of Germany. The German Hound is of the scenthound",
    "timestamp": "2018-10-17T20:55:39Z"
  },
  {
    "ns": 0,
    "title": "London Tipton",
    "pageid": 2470063,
    "size": 40038,
    "wordcount": 5505,
    "snippet": "to her as 'Cranky Maddie'. Ivana (voiced by Emma Stone) is London's <span class=\"searchmatch\">pomeranian</span> <span class=\"searchmatch\">dog</span>, who is treated like royalty. She is seen in an episode that she can",
    "timestamp": "2018-10-19T22:21:44Z"
  },
  {
    "ns": 0,
    "title": "Miniature Dachshund",
    "pageid": 1751433,
    "size": 6391,
    "wordcount": 842,
    "snippet": "The name dachshund comes from the German words dachs (badger) and hund (<span class=\"searchmatch\">dog</span>). Dachshunds first came to the United States in 1870, imported to hunt rabbits",
    "timestamp": "2018-10-17T13:58:32Z"
  },
  {
    "ns": 0,
    "title": "Rottweiler",
    "pageid": 271052,
    "size": 31643,
    "wordcount": 4046,
    "snippet": "The Rottweiler (/\u02c8r\u0252twa\u026al\u0259r/, UK also /-va\u026al\u0259r/) is a breed of domestic <span class=\"searchmatch\">dog</span>, regarded as medium-to-large or large. The dogs were known in German as Rottweiler",
    "timestamp": "2018-10-30T12:21:58Z"
  },
  {
    "ns": 0,
    "title": "German Shepherd",
    "pageid": 79289,
    "size": 58378,
    "wordcount": 6086,
    "snippet": "large-sized working <span class=\"searchmatch\">dog</span> that originated in Germany. In the English language, the breed's officially recognized name is German Shepherd <span class=\"searchmatch\">Dog</span> (sometimes abbreviated",
    "timestamp": "2018-10-30T05:22:44Z"
  },
  {
    "ns": 0,
    "title": "Large M\u00fcnsterl\u00e4nder",
    "pageid": 2416829,
    "size": 5921,
    "wordcount": 603,
    "snippet": "The Large M\u00fcnsterl\u00e4nder (or Gro\u00dfer M\u00fcnsterl\u00e4nder) is a breed of gun <span class=\"searchmatch\">dog</span> originally from the M\u00fcnster region in Germany. The first breed club was founded",
    "timestamp": "2018-10-17T22:03:25Z"
  },
  {
    "ns": 0,
    "title": "Dog breed",
    "pageid": 79676,
    "size": 34861,
    "wordcount": 3616,
    "snippet": "Shepherd <span class=\"searchmatch\">Dog</span> Catahoula Leopard <span class=\"searchmatch\">Dog</span> Chesapeake Bay Retriever <span class=\"searchmatch\">Pomeranian</span> (unknown variety) Curly-coated Retriever Flat-coated Retriever German Shepherd <span class=\"searchmatch\">Dog</span> Golden",
    "timestamp": "2018-10-28T09:50:56Z"
  },
  {
    "ns": 0,
    "title": "List of Best in Show winners of the Westminster Kennel Club Dog Show",
    "pageid": 15832990,
    "size": 53125,
    "wordcount": 2440,
    "snippet": "German Shepherd <span class=\"searchmatch\">Dog</span> Club of America. Retrieved 11 April 2010. &quot;Honors: Ch. Great Elms Prince Charming II&quot;. Central Caroline <span class=\"searchmatch\">Pomeranian</span> Club. Archived from",
    "timestamp": "2018-07-28T14:39:49Z"
  },
  {
    "ns": 0,
    "title": "German Wirehaired Pointer",
    "pageid": 519126,
    "size": 10240,
    "wordcount": 1229,
    "snippet": "large-sized griffon type breed of <span class=\"searchmatch\">dog</span> developed in the 19th century in Germany for hunting. It became a leading gun <span class=\"searchmatch\">dog</span> in Germany in the later part of",
    "timestamp": "2018-10-17T21:56:04Z"
  },
  {
    "ns": 0,
    "title": "List of fictional dogs in live-action film",
    "pageid": 52975160,
    "size": 52162,
    "wordcount": 103,
    "snippet": "<span class=\"searchmatch\">dog</span> who has the uncanny ability to play basketball. Buster Dachshund Toy Story 2, Toy Story 3 Andy's <span class=\"searchmatch\">dog</span>, but more loyal to Woody. Camille <span class=\"searchmatch\">Pomeranian</span>",
    "timestamp": "2018-09-17T17:24:11Z"
  },
  {
    "ns": 0,
    "title": "Kromfohrl\u00e4nder",
    "pageid": 5370471,
    "size": 5570,
    "wordcount": 623,
    "snippet": "(/\u02c8kro\u028amf\u0259rl\u00e6nd\u0259r/ KROHM-f\u0259r-land-\u0259r) is a breed of <span class=\"searchmatch\">dog</span> that originated in Germany. It is used as a companion <span class=\"searchmatch\">dog</span>. The Kromfohrlander comes in 2 coat variations:",
    "timestamp": "2018-10-29T04:21:24Z"
  },
  {
    "ns": 0,
    "title": "Weimaraner",
    "pageid": 519161,
    "size": 15956,
    "wordcount": 1705,
    "snippet": "The Weimaraner (/\u02c8va\u026am\u0259r\u0251\u02d0n\u0259r/ VY-m\u0259-rah-n\u0259r) is a large <span class=\"searchmatch\">dog</span> that was originally bred for hunting in the early 19th century. Early Weimaraners were used",
    "timestamp": "2018-10-17T21:59:15Z"
  },
  {
    "ns": 0,
    "title": "Volpino Italiano",
    "pageid": 1750964,
    "size": 6531,
    "wordcount": 727,
    "snippet": "pronunciation:\u00a0[vol\u02c8pi\u02d0no ita\u02c8lja\u02d0no]; literally, &quot;Italian foxy [<span class=\"searchmatch\">dog</span>]&quot;) is a spitz-type breed of <span class=\"searchmatch\">dog</span> originally from Italy. Spitz-type dogs were found throughout",
    "timestamp": "2018-10-17T16:53:31Z"
  },
  {
    "ns": 0,
    "title": "The Intelligence of Dogs",
    "pageid": 30874722,
    "size": 12134,
    "wordcount": 1072,
    "snippet": "Brittany Cocker Spaniel Weimaraner Belgian Malinois Bernese Mountain <span class=\"searchmatch\">Dog</span> <span class=\"searchmatch\">Pomeranian</span> Irish Water Spaniel Vizsla Cardigan Welsh Corgi Understanding of New",
    "timestamp": "2018-10-14T19:03:26Z"
  },
  {
    "ns": 0,
    "title": "Dobermann",
    "pageid": 2139688,
    "size": 38638,
    "wordcount": 4392,
    "snippet": "Pinscher in the United States and Canada, is a medium-large breed of domestic <span class=\"searchmatch\">dog</span> that was originally developed around 1890 by Karl Friedrich Louis Dobermann",
    "timestamp": "2018-10-30T13:18:55Z"
  },
  {
    "ns": 0,
    "title": "Elo (dog)",
    "pageid": 8675445,
    "size": 5171,
    "wordcount": 612,
    "snippet": "The Elo is an emerging breed of <span class=\"searchmatch\">dog</span>, with development beginning in 1987 in Germany. The breed name is trademarked and development has been closely supervised",
    "timestamp": "2018-09-07T23:01:22Z"
  },
  {
    "ns": 0,
    "title": "Boxer (dog)",
    "pageid": 253409,
    "size": 36107,
    "wordcount": 4059,
    "snippet": "The Boxer is a medium-sized, short-haired breed of <span class=\"searchmatch\">dog</span>, developed in Germany. The coat is smooth and tight-fitting; colors are fawn or brindled, with",
    "timestamp": "2018-10-28T22:24:23Z"
  },
  {
    "ns": 0,
    "title": "Leonberger",
    "pageid": 2165498,
    "size": 29003,
    "wordcount": 3026,
    "snippet": "&quot;symbolic <span class=\"searchmatch\">dog</span>&quot; that would mimic the lion in the town crest. It is in the Working Group for <span class=\"searchmatch\">dog</span> shows such as Crufts, but not at the World <span class=\"searchmatch\">Dog</span> Show. This",
    "timestamp": "2018-10-17T12:49:37Z"
  },
  {
    "ns": 0,
    "title": "Dachshund",
    "pageid": 8518,
    "size": 54212,
    "wordcount": 5906,
    "snippet": "/\u02c8d\u0251\u02d0ks\u0259nt/) (English: badger <span class=\"searchmatch\">dog</span>; also known as the sausage <span class=\"searchmatch\">dog</span> or wiener <span class=\"searchmatch\">dog</span>) is a short-legged, long-bodied, hound-type <span class=\"searchmatch\">dog</span> breed. The standard size dachshund",
    "timestamp": "2018-10-29T23:22:37Z"
  },
  {
    "ns": 0,
    "title": "Dog crossbreed",
    "pageid": 825162,
    "size": 19176,
    "wordcount": 2180,
    "snippet": "are dogs which have been intentionally bred from two or more recognized <span class=\"searchmatch\">dog</span> breeds and not from dogs with no purebred ancestors, but have not been artificially",
    "timestamp": "2018-08-03T05:43:23Z"
  },
  {
    "ns": 0,
    "title": "Small M\u00fcnsterl\u00e4nder",
    "pageid": 1280850,
    "size": 10296,
    "wordcount": 1376,
    "snippet": "SM or Kleiner M\u00fcnsterl\u00e4nder) is a versatile hunting-pointing-retrieving <span class=\"searchmatch\">dog</span> breed that reached its current form in the area around M\u00fcnster, Germany.",
    "timestamp": "2018-10-17T22:04:16Z"
  },
  {
    "ns": 0,
    "title": "Quigley (film)",
    "pageid": 44890000,
    "size": 4837,
    "wordcount": 385,
    "snippet": "Quigley, released in the United Kingdom as Daddy <span class=\"searchmatch\">Dog</span> Day, is a 2003 family comedy film that was directed by William Byron Hillman. It was released straight",
    "timestamp": "2018-04-06T01:36:21Z"
  },
  {
    "ns": 0,
    "title": "German Shorthaired Pointer",
    "pageid": 519105,
    "size": 19745,
    "wordcount": 2493,
    "snippet": "sized breed of <span class=\"searchmatch\">dog</span> developed in the 19th century in Germany for hunting. A versatile hunting breed, being an all-purpose gun breed of <span class=\"searchmatch\">dog</span> suitable for both",
    "timestamp": "2018-10-30T13:54:43Z"
  },
  {
    "ns": 0,
    "title": "German Pinscher",
    "pageid": 3909839,
    "size": 10014,
    "wordcount": 1088,
    "snippet": "(original name Deutscher Pinscher, FCI No. 184) is a medium-sized breed of <span class=\"searchmatch\">dog</span>, a Pinscher type that originated in Germany. The breed is included in the",
    "timestamp": "2018-10-17T12:35:59Z"
  },
  {
    "ns": 0,
    "title": "German Longhaired Pointer",
    "pageid": 5505529,
    "size": 10157,
    "wordcount": 1009,
    "snippet": "The German longhaired pointer (GLP) is a breed of <span class=\"searchmatch\">dog</span>. Developed in Germany, it is used as a multipurpose gundog. It is closely related to its cousins",
    "timestamp": "2018-10-17T22:03:06Z"
  },
  {
    "ns": 0,
    "title": "List of dog breeds",
    "pageid": 8615,
    "size": 88135,
    "wordcount": 533,
    "snippet": " a breed's origin overlaps the boundaries of two or more countries; the <span class=\"searchmatch\">dog</span> is normally listed only in the country with which it is most commonly associated;",
    "timestamp": "2018-10-27T20:36:25Z"
  },
  {
    "ns": 0,
    "title": "Jagdterrier",
    "pageid": 1254130,
    "size": 10640,
    "wordcount": 1379,
    "snippet": "Crufts in 1886, and was the largest <span class=\"searchmatch\">dog</span> show in the world before World War I, while the first breed-specific <span class=\"searchmatch\">dog</span> publication anywhere was a magazine devoted",
    "timestamp": "2018-10-17T13:23:47Z"
  },
  {
    "ns": 0,
    "title": "L\u00f6wchen",
    "pageid": 1741676,
    "size": 9114,
    "wordcount": 929,
    "snippet": "L\u00f6wchen or Little Lion <span class=\"searchmatch\">Dog</span> (German: L\u00f6wchen, &quot;little lion&quot;; French: Petit chien lion, &quot;little lion <span class=\"searchmatch\">dog</span>&quot;) is a breed of <span class=\"searchmatch\">dog</span>. A small <span class=\"searchmatch\">dog</span>, they are considered",
    "timestamp": "2018-10-16T17:34:42Z"
  },
  {
    "ns": 0,
    "title": "German Spaniel",
    "pageid": 10979089,
    "size": 10658,
    "wordcount": 1151,
    "snippet": "Wachtelhund (German quail <span class=\"searchmatch\">dog</span>), is a breed of <span class=\"searchmatch\">dog</span> that was developed in Germany around 1890, and is used as a hunting <span class=\"searchmatch\">dog</span>. Descended from the old German",
    "timestamp": "2018-10-16T19:07:59Z"
  },
  {
    "ns": 0,
    "title": "Cavalier King Charles Spaniel",
    "pageid": 338810,
    "size": 46850,
    "wordcount": 4978,
    "snippet": "Japanese and <span class=\"searchmatch\">Pomeranians</span>&quot; published under the name of the &quot;Hon. Mrs Neville Lytton&quot; in 1911. In 1926, the American Roswell Eldridge offered a <span class=\"searchmatch\">dog</span> show class",
    "timestamp": "2018-10-23T17:42:31Z"
  },
  {
    "ns": 0,
    "title": "White Shepherd",
    "pageid": 1543132,
    "size": 20073,
    "wordcount": 2577,
    "snippet": "Shepherd <span class=\"searchmatch\">dog</span> in Canada and the United States and from European imports. The German Shepherd and the white German Shepherd are the same <span class=\"searchmatch\">dog</span>, though their",
    "timestamp": "2018-10-16T13:11:04Z"
  },
  {
    "ns": 0,
    "title": "Cephalic index",
    "pageid": 37268,
    "size": 16076,
    "wordcount": 1528,
    "snippet": "Norfolk Terrier Norwich Terrier Papillon Pembroke Welsh Corgi Phal\u00e8ne <span class=\"searchmatch\">Pomeranian</span> Rottweiler \u0160arplaninac St. Bernard Samoyed Siberian Husky Vizsla Weimaraner",
    "timestamp": "2018-10-21T17:02:03Z"
  },
  {
    "ns": 0,
    "title": "Shetland Sheepdog",
    "pageid": 177575,
    "size": 31239,
    "wordcount": 3556,
    "snippet": "The Shetland Sheepdog, also known as the Sheltie, is a breed of herding <span class=\"searchmatch\">dog</span> that originated in the Shetland Islands, Scotland. The original name of this",
    "timestamp": "2018-10-25T14:40:24Z"
  },
  {
    "ns": 0,
    "title": "Toy Trawler Spaniel",
    "pageid": 25242924,
    "size": 4531,
    "wordcount": 500,
    "snippet": "Sussex Spaniel. It was originally used as a sporting <span class=\"searchmatch\">dog</span>, but became used as a toy and show <span class=\"searchmatch\">dog</span>. It was considered to be on the verge of extinction by",
    "timestamp": "2018-07-25T21:29:20Z"
  },
  {
    "ns": 0,
    "title": "Terrier",
    "pageid": 176426,
    "size": 10020,
    "wordcount": 1191,
    "snippet": "A terrier is a <span class=\"searchmatch\">dog</span> of any one of many breeds or landraces of the terrier type, which are typically small, wiry and fearless.[citation needed] Terrier",
    "timestamp": "2018-10-23T15:48:47Z"
  },
  {
    "ns": 0,
    "title": "FCI Spitz and Primitive Types Group",
    "pageid": 26616873,
    "size": 4174,
    "wordcount": 355,
    "snippet": "Mittelspitz d) Kleinspitz e) Zwergspitz (<span class=\"searchmatch\">Pomeranian</span>) 2. Italy Volpino Italiano 1. China Chow Chow 2. Korea Korea Jindo <span class=\"searchmatch\">Dog</span> 3. Germany Eurasier 4. Japan Akita",
    "timestamp": "2018-10-14T13:22:19Z"
  },
  {
    "ns": 0,
    "title": "Giant Schnauzer",
    "pageid": 1286520,
    "size": 16840,
    "wordcount": 1485,
    "snippet": "The Giant Schnauzer is a working breed of <span class=\"searchmatch\">dog</span> developed in the 17th century in Germany. It is the largest of the three breeds of Schnauzer\u2014the other two",
    "timestamp": "2018-10-17T12:37:11Z"
  },
  {
    "ns": 0,
    "title": "List of fictional dogs in video games",
    "pageid": 34581060,
    "size": 13091,
    "wordcount": 54,
    "snippet": "She assists Rinoa in most of her Limit Breaks. Annoying <span class=\"searchmatch\">Dog</span> Undertale PC\u00a0\u00b7 PlayStation 4 A <span class=\"searchmatch\">dog</span> who represents the game's creator, Toby Fox. It often steals",
    "timestamp": "2018-09-06T07:19:52Z"
  },
  {
    "ns": 0,
    "title": "Yorkshire Terrier",
    "pageid": 361299,
    "size": 48156,
    "wordcount": 5480,
    "snippet": "The Yorkshire Terrier is a small <span class=\"searchmatch\">dog</span> breed of terrier type, developed during the 19th century in Yorkshire, England, to catch rats in clothing mills.",
    "timestamp": "2018-10-18T21:05:55Z"
  },
  {
    "ns": 0,
    "title": "List of fictional dogs in animated film",
    "pageid": 52975288,
    "size": 16923,
    "wordcount": 30,
    "snippet": "Oliver Twist by English author Charles Dickens. Gigdet <span class=\"searchmatch\">Pomeranian</span> The Secret Life of Pets <span class=\"searchmatch\">Dog</span> with an unnamed owner; has a crush on Max. Gigi alien experiment",
    "timestamp": "2018-08-31T18:22:31Z"
  },
  {
    "ns": 0,
    "title": "Pembroke Welsh Corgi",
    "pageid": 515508,
    "size": 17466,
    "wordcount": 1779,
    "snippet": "The Pembroke Welsh Corgi (/\u02c8k\u0254\u02d0r\u0261i/; Welsh for &quot;dwarf <span class=\"searchmatch\">dog</span>&quot;) is a cattle herding <span class=\"searchmatch\">dog</span> breed which originated in Pembrokeshire, Wales. It is one of two breeds",
    "timestamp": "2018-10-23T16:39:22Z"
  },
  {
    "ns": 0,
    "title": "Mr. Winkle",
    "pageid": 1874699,
    "size": 4290,
    "wordcount": 515,
    "snippet": "Mr. Winkle (born 1996) is the name of a very small <span class=\"searchmatch\">dog</span> of uncertain breed (possibly <span class=\"searchmatch\">Pomeranian</span>/Chihuahua) whose cute and comical appearance has made him",
    "timestamp": "2018-09-06T00:26:10Z"
  },
  {
    "ns": 0,
    "title": "Lisa Vanderpump",
    "pageid": 38789274,
    "size": 16798,
    "wordcount": 1328,
    "snippet": "6 November 2014. In 2015, Lisa Vanderpump (along with her husband and <span class=\"searchmatch\">Pomeranian</span>, &quot;Giggy&quot;) launched a line of luxury pet accessories, Vanderpump Pets.",
    "timestamp": "2018-10-08T08:08:07Z"
  },
  {
    "ns": 0,
    "title": "Aging in dogs",
    "pageid": 9659164,
    "size": 24758,
    "wordcount": 2751,
    "snippet": "breed, and affects the <span class=\"searchmatch\">dog</span>'s health, physical ability and life expectancy. As with humans, advanced years often bring changes in a <span class=\"searchmatch\">dog</span>'s ability to hear,",
    "timestamp": "2018-10-17T22:06:21Z"
  },
  {
    "ns": 0,
    "title": "Herman B. Duryea",
    "pageid": 2529936,
    "size": 4819,
    "wordcount": 579,
    "snippet": "for a <span class=\"searchmatch\">dog</span>'s funeral;occurred on Saturday, October 24th, 1914, less than three months after the World War began. The <span class=\"searchmatch\">dog</span> was Betty 2nd, a <span class=\"searchmatch\">Pomeranian</span> belonging",
    "timestamp": "2018-01-08T13:28:00Z"
  },
  {
    "ns": 0,
    "title": "Canine reproduction",
    "pageid": 5740890,
    "size": 33780,
    "wordcount": 3899,
    "snippet": "variability in the maturation age between breeds, and even within a breed of <span class=\"searchmatch\">dog</span>. 1. Proestrus, in which eggs in the ovaries begin to mature and estrogen",
    "timestamp": "2018-10-13T18:26:05Z"
  },
  {
    "ns": 0,
    "title": "Coat (dog)",
    "pageid": 1681022,
    "size": 39226,
    "wordcount": 3915,
    "snippet": "The coat of the domestic <span class=\"searchmatch\">dog</span> (Canis lupus familiaris) refers to the hair that covers its body. A <span class=\"searchmatch\">dog</span>'s coat may be a double coat, made up of a soft undercoat",
    "timestamp": "2018-09-22T03:10:20Z"
  },
  {
    "ns": 0,
    "title": "Maltese dog",
    "pageid": 466712,
    "size": 30083,
    "wordcount": 2856,
    "snippet": "(Italian:\u00a0[mal\u02c8te\u02d0ze]), Canis familiaris Maelitacus, is a small breed of <span class=\"searchmatch\">dog</span> in the Toy Group. It descends from dogs originating in the Central Mediterranean",
    "timestamp": "2018-10-18T17:42:28Z"
  },
  {
    "ns": 0,
    "title": "Pom",
    "pageid": 368000,
    "size": 1747,
    "wordcount": 205,
    "snippet": "Ontology Model, a method for ontology learning used in KAON <span class=\"searchmatch\">Pomeranian</span> (<span class=\"searchmatch\">dog</span>), a breed of <span class=\"searchmatch\">dog</span> Princeton Ocean Model, a model for ocean circulation Pattern-oriented",
    "timestamp": "2018-10-17T08:18:09Z"
  },
  {
    "ns": 0,
    "title": "Baba",
    "pageid": 98277,
    "size": 3885,
    "wordcount": 495,
    "snippet": "Baba, Mogilno County in Kuyavian-<span class=\"searchmatch\">Pomeranian</span> Voivodeship (north-central Poland) Baba, Rypin County in Kuyavian-<span class=\"searchmatch\">Pomeranian</span> Voivodeship (north-central Poland)",
    "timestamp": "2018-10-29T02:16:35Z"
  },
  {
    "ns": 0,
    "title": "Jonathan Philip Klein",
    "pageid": 50531458,
    "size": 12673,
    "wordcount": 1345,
    "snippet": "a <span class=\"searchmatch\">dog</span> wanted most, and then used that as a reward to encourage positive behavior; for example, in one instance, he found that a difficult <span class=\"searchmatch\">Pomeranian</span> valued",
    "timestamp": "2017-12-11T10:06:28Z"
  },
  {
    "ns": 0,
    "title": "Animals aboard the RMS Titanic",
    "pageid": 35285726,
    "size": 10385,
    "wordcount": 1336,
    "snippet": "Jacob Astor. A <span class=\"searchmatch\">Pomeranian</span> owned by Margaret Bechstein Hays, named Bebe, which she kept (probably surreptitiously) in her cabin. A <span class=\"searchmatch\">dog</span> owned by Elizabeth",
    "timestamp": "2018-10-18T15:06:23Z"
  },
  {
    "ns": 0,
    "title": "The Lady with the Dog",
    "pageid": 17698836,
    "size": 18210,
    "wordcount": 2346,
    "snippet": "&quot;The Lady with the <span class=\"searchmatch\">Dog</span>&quot; (Russian: \u0414\u0430\u043c\u0430 \u0441 \u0441\u043e\u0431\u0430\u0447\u043a\u043e\u0439, translit.\u00a0Dama s sobachkoy) is a short story by Anton Chekhov. First published in 1899, it describes",
    "timestamp": "2018-09-26T21:33:04Z"
  },
  {
    "ns": 0,
    "title": "West Highland White Terrier",
    "pageid": 475802,
    "size": 30751,
    "wordcount": 3486,
    "snippet": "Terriers and other breeds including Beagles and <span class=\"searchmatch\">Pomeranians</span>. It is a neurological disease where the <span class=\"searchmatch\">dog</span> lacks an enzyme called galactosylceramidase. The",
    "timestamp": "2018-10-17T13:33:35Z"
  },
  {
    "ns": 0,
    "title": "Shetland animal breeds",
    "pageid": 12689865,
    "size": 6810,
    "wordcount": 728,
    "snippet": "was heavily crossed with other dogs including the Rough Collie and the <span class=\"searchmatch\">Pomeranian</span>, and the modern Shetland or &quot;Sheltie&quot; now resembles a miniature Rough",
    "timestamp": "2018-06-15T04:49:46Z"
  },
  {
    "ns": 0,
    "title": "Demodex",
    "pageid": 971469,
    "size": 14444,
    "wordcount": 1515,
    "snippet": "animals host different species of Demodex. Demodex canis lives on the domestic <span class=\"searchmatch\">dog</span>. Infestation with Demodex is common and usually does not cause any symptoms",
    "timestamp": "2018-09-10T16:55:18Z"
  },
  {
    "ns": 0,
    "title": "1st Armoured Brigade (Poland)",
    "pageid": 12501698,
    "size": 1844,
    "wordcount": 180,
    "snippet": "subordinate to the Polish First Army. Later the unit fought in the East <span class=\"searchmatch\">Pomeranian</span> Offensive. In January 1945 it received another honorary name, Warszawska",
    "timestamp": "2018-10-16T02:07:14Z"
  },
  {
    "ns": 0,
    "title": "Margaret Bechstein Hays",
    "pageid": 35176122,
    "size": 7994,
    "wordcount": 802,
    "snippet": "wrapped Hays' <span class=\"searchmatch\">Pomeranian</span> <span class=\"searchmatch\">dog</span> in blankets. They headed to C Deck, where Tucker helped them collect life jackets. The three women and the <span class=\"searchmatch\">dog</span> boarded lifeboat",
    "timestamp": "2018-09-06T00:24:13Z"
  },
  {
    "ns": 0,
    "title": "Florence Nagle",
    "pageid": 44075819,
    "size": 38673,
    "wordcount": 4429,
    "snippet": "Royal Air Force. As a child, Nagle had a <span class=\"searchmatch\">Pomeranian</span> and a Bulldog, but was promised she could have a larger <span class=\"searchmatch\">dog</span> once her schooling was completed. In 1913",
    "timestamp": "2018-05-22T00:51:24Z"
  },
  {
    "ns": 0,
    "title": "Missile (Ghost Trick)",
    "pageid": 30838355,
    "size": 8548,
    "wordcount": 1008,
    "snippet": "he tells fortunes to players in his &quot;enthusiastic&quot; style. Missile is a <span class=\"searchmatch\">Pomeranian</span> with thick fur of two colours: brown and white. He is very excitable,",
    "timestamp": "2018-04-02T17:20:08Z"
  },
  {
    "ns": 0,
    "title": "Standard Schnauzer",
    "pageid": 1272987,
    "size": 29752,
    "wordcount": 3504,
    "snippet": "The Standard Schnauzer (Mittelschnauzer) is a <span class=\"searchmatch\">dog</span> breed that originated in Germany from at least 14th-15th century, of Schnauzer breed type and progenitor",
    "timestamp": "2018-10-17T12:37:59Z"
  },
  {
    "ns": 0,
    "title": "Dog with a Blog",
    "pageid": 36190455,
    "size": 30555,
    "wordcount": 2795,
    "snippet": "<span class=\"searchmatch\">Dog</span> with a Blog is an American comedy television series that aired on Disney Channel, premiering on October 12, 2012, and ending on September 25, 2015",
    "timestamp": "2018-10-09T12:45:52Z"
  },
  {
    "ns": 0,
    "title": "Balto (film)",
    "pageid": 1487971,
    "size": 19686,
    "wordcount": 2224,
    "snippet": "Universal Pictures. The film is loosely based on a true story about the <span class=\"searchmatch\">dog</span> of the same name who helped save children from the diphtheria epidemic in",
    "timestamp": "2018-10-21T16:19:35Z"
  },
  {
    "ns": 0,
    "title": "Hilda Eisen",
    "pageid": 58859633,
    "size": 9055,
    "wordcount": 821,
    "snippet": "sold eggs and raised chickens while her husband also worked at a Vernon hot <span class=\"searchmatch\">dog</span> factory cleaning meat barrels. Eisen and her husband Harry saved money to",
    "timestamp": "2018-10-25T02:36:36Z"
  },
  {
    "ns": 0,
    "title": "Lady and the Tramp II: Scamp's Adventure",
    "pageid": 286830,
    "size": 20584,
    "wordcount": 2236,
    "snippet": "served as the supervising animator for him. Alyssa Milano as Angel, a <span class=\"searchmatch\">Pomeranian</span> mix Chihuahua who was once a pet and Scamp's love interest. She has a",
    "timestamp": "2018-10-28T19:33:25Z"
  },
  {
    "ns": 0,
    "title": "Griffon Bruxellois",
    "pageid": 1377361,
    "size": 16183,
    "wordcount": 1750,
    "snippet": "The Griffon Bruxellois or Brussels Griffon is a breed of toy <span class=\"searchmatch\">dog</span>, named for their city of origin: Brussels, Belgium. The Griffon Bruxellois may refer",
    "timestamp": "2018-10-16T19:27:16Z"
  },
  {
    "ns": 0,
    "title": "Luxating patella",
    "pageid": 949631,
    "size": 6634,
    "wordcount": 716,
    "snippet": "and toy Poodles, Maltese, Jack Russell Terriers, Yorkshire Terriers, <span class=\"searchmatch\">Pomeranians</span>, Pekingese, Patterdale Terriers, Chihuahuas, Cavalier King Charles Spaniels",
    "timestamp": "2018-07-27T08:53:54Z"
  },
  {
    "ns": 0,
    "title": "Companion group",
    "pageid": 3692999,
    "size": 12577,
    "wordcount": 394,
    "snippet": "group of dogs, used by kennel clubs to classify a defined collection of <span class=\"searchmatch\">dog</span> breeds, and does not necessarily include all dogs kept as companions or pets",
    "timestamp": "2018-03-02T12:57:31Z"
  },
  {
    "ns": 0,
    "title": "Navleen Kumar",
    "pageid": 30490428,
    "size": 4009,
    "wordcount": 480,
    "snippet": "June, at around 7:30 AM Indian Time, while she was walking her two dogs (<span class=\"searchmatch\">Pomeranian</span> breed) on the terrace of her apartment building, she was attacked by a",
    "timestamp": "2016-12-05T00:18:48Z"
  },
  {
    "ns": 0,
    "title": "List of dog breeds recognized by the American Kennel Club",
    "pageid": 26905910,
    "size": 8211,
    "wordcount": 703,
    "snippet": "Lowland Sheepdog, Herding <span class=\"searchmatch\">Pomeranian</span>, Toy Poodle, Non-Sporting &amp; Toy Portuguese Podengo Pequeno, Hound Portuguese Water <span class=\"searchmatch\">Dog</span>, Working Pug, Toy Puli, Herding",
    "timestamp": "2018-10-19T06:03:12Z"
  },
  {
    "ns": 0,
    "title": "Free City of Danzig",
    "pageid": 471230,
    "size": 90939,
    "wordcount": 10084,
    "snippet": "ISBN\u00a0978-0-8143-1662-7. Those congregations in Polish-annexed West Prussia (<span class=\"searchmatch\">Pomeranian</span> Voivodeship) merged into the new United Evangelical Church in Poland,",
    "timestamp": "2018-10-28T14:24:31Z"
  },
  {
    "ns": 0,
    "title": "Golden Collar Awards",
    "pageid": 35053635,
    "size": 3479,
    "wordcount": 399,
    "snippet": "Best <span class=\"searchmatch\">Dog</span> in a Reality Television Series\u00a0: tie Giggy, <span class=\"searchmatch\">Pomeranian</span>, in The Real Housewives of Beverly Hills, and Hercules, Pit bull, in Pit Boss Best <span class=\"searchmatch\">Dog</span> in",
    "timestamp": "2017-12-05T21:56:16Z"
  },
  {
    "ns": 0,
    "title": "Breed All About It",
    "pageid": 5899739,
    "size": 5707,
    "wordcount": 236,
    "snippet": "Breed All About It was a show that headlined one breed of <span class=\"searchmatch\">dog</span>, or a group of dogs, and presented facts and advice about that breed. It was aired Animal",
    "timestamp": "2017-04-06T20:32:42Z"
  },
  {
    "ns": 0,
    "title": "100 Deeds for Eddie McDowd",
    "pageid": 1247750,
    "size": 5858,
    "wordcount": 625,
    "snippet": "Eddie's friend and next-door neighbor. Gigi (voiced by Alyson Hannigan) \u2013 A <span class=\"searchmatch\">Pomeranian</span> that Eddie is often smitten by. The series was cancelled in the United",
    "timestamp": "2018-10-25T03:48:04Z"
  },
  {
    "ns": 0,
    "title": "Dogs 101",
    "pageid": 22321817,
    "size": 6720,
    "wordcount": 172,
    "snippet": "Dogs 101 is a show that airs on an American TV channel Animal Planet. <span class=\"searchmatch\">Dog</span> trainers and breeding experts explored the advantages and disadvantages of various",
    "timestamp": "2018-05-05T05:42:55Z"
  },
  {
    "ns": 0,
    "title": "Inubaka: Crazy for Dogs",
    "pageid": 8652739,
    "size": 44093,
    "wordcount": 7334,
    "snippet": "puppy be trained to be a service <span class=\"searchmatch\">dog</span>, even though John's owner already took one of Noa's yellow puppies. Czerny A <span class=\"searchmatch\">Pomeranian</span> belonging to Kanako-sensei. She",
    "timestamp": "2018-08-05T13:04:09Z"
  },
  {
    "ns": 0,
    "title": "Aho-Girl",
    "pageid": 45159471,
    "size": 48307,
    "wordcount": 2801,
    "snippet": "15, 21, 28 She love Yoshio (Yoshiko in disguise). <span class=\"searchmatch\">Dog</span> (\u72ac, Inu) Voiced by: Daisuke Namikawa A big <span class=\"searchmatch\">dog</span> that Yoshiko takes a liking to and would like to ride",
    "timestamp": "2018-10-15T11:23:46Z"
  },
  {
    "ns": 0,
    "title": "Zentarr Elizabeth",
    "pageid": 35049816,
    "size": 8714,
    "wordcount": 780,
    "snippet": "Zentarr Elizabeth (2005\u20132017), also known as Elizabeth, was a Lhasa Apso show <span class=\"searchmatch\">dog</span> bred and handled by Margaret Anderson who won Best in Show at Crufts in 2012",
    "timestamp": "2018-06-20T09:56:10Z"
  },
  {
    "ns": 0,
    "title": "French Spaniel",
    "pageid": 7376590,
    "size": 15774,
    "wordcount": 1628,
    "snippet": "(Epagneul Fran\u00e7ais) is a breed of <span class=\"searchmatch\">dog</span> of the Spaniel-like setter. It was developed in France and Canada as a hunting <span class=\"searchmatch\">dog</span>, descended from dogs of the 14th",
    "timestamp": "2018-10-17T22:02:49Z"
  },
  {
    "ns": 0,
    "title": "Lick granuloma",
    "pageid": 3987221,
    "size": 12712,
    "wordcount": 1342,
    "snippet": "commonly in dogs, but also in cats. In dogs, it results typically from the <span class=\"searchmatch\">dog</span>'s urge to lick the lower portion of one of his or her legs. The lesion can",
    "timestamp": "2018-05-14T20:29:19Z"
  },
  {
    "ns": 0,
    "title": "Nintendogs + Cats",
    "pageid": 27756027,
    "size": 11786,
    "wordcount": 1153,
    "snippet": "breeds which include the French Bulldog, Basset Hound, Great Dane and <span class=\"searchmatch\">Pomeranian</span>. There are three cat varieties that appear in each version of the game",
    "timestamp": "2018-10-11T19:43:39Z"
  },
  {
    "ns": 0,
    "title": "Henning von Tresckow",
    "pageid": 895553,
    "size": 31470,
    "wordcount": 4049,
    "snippet": "be done. This is our only chance... Hitler must be cut down like a rabid <span class=\"searchmatch\">dog</span>.&quot; (1943) &quot;I cannot understand how people can still call themselves Christians",
    "timestamp": "2018-10-01T21:57:49Z"
  },
  {
    "ns": 0,
    "title": "Denyse Tontz",
    "pageid": 39113400,
    "size": 13297,
    "wordcount": 966,
    "snippet": " Nikki is sweet and talented but also initially quite na\u00efve, and her <span class=\"searchmatch\">pomeranian</span> Evita becomes the object of Stan's affection. It was later announced that",
    "timestamp": "2018-08-18T19:45:18Z"
  },
  {
    "ns": 0,
    "title": "List of Dog with a Blog episodes",
    "pageid": 37010459,
    "size": 81096,
    "wordcount": 1808,
    "snippet": "<span class=\"searchmatch\">Dog</span> with a Blog is an American comedy television series that aired on Disney Channel, premiering on October 12, 2012, and ending on September 25, 2015",
    "timestamp": "2018-10-30T14:57:38Z"
  },
  {
    "ns": 0,
    "title": "Fortune Dogs",
    "pageid": 9882680,
    "size": 8493,
    "wordcount": 1035,
    "snippet": "for police as sniffing <span class=\"searchmatch\">dog</span>, and always travel with Grace. Police <span class=\"searchmatch\">Dog</span> - Giant Schnauzer Police <span class=\"searchmatch\">Dog</span> - English Pointer Police <span class=\"searchmatch\">Dog</span> - English Pointer Myna",
    "timestamp": "2018-03-21T02:11:07Z"
  },
  {
    "ns": 0,
    "title": "1777 in art",
    "pageid": 7456594,
    "size": 5260,
    "wordcount": 445,
    "snippet": "Conde de Campomanes Thomas Gainsborough Portrait of his daughter Mary <span class=\"searchmatch\">Pomeranian</span> Bitch and Puppy (&quot;Two Fox Dogs&quot; \u2013 approximate date) Francisco Goya \u2013 The",
    "timestamp": "2018-02-04T14:52:59Z"
  },
  {
    "ns": 0,
    "title": "Turi",
    "pageid": 11245675,
    "size": 1611,
    "wordcount": 192,
    "snippet": "with origins in India, also known as Aheria Turi, one of Queen Victoria's pets, a <span class=\"searchmatch\">Pomeranian</span> (<span class=\"searchmatch\">dog</span>) Massachusetts Toxics Use Reduction Institute (TURI)",
    "timestamp": "2018-05-16T20:20:15Z"
  },
  {
    "ns": 0,
    "title": "Jerusalem (disambiguation)",
    "pageid": 264452,
    "size": 6634,
    "wordcount": 745,
    "snippet": "village in England Jeruzalem, Ljutomer, village in Slovenia Jeruzalem, <span class=\"searchmatch\">Pomeranian</span> Voivodeship, village in Poland Jerusalem (K\u00f6nigsberg), former quarter",
    "timestamp": "2018-07-04T18:15:52Z"
  },
  {
    "ns": 0,
    "title": "Afterglow Maverick Sabre",
    "pageid": 42161771,
    "size": 13054,
    "wordcount": 1066,
    "snippet": "Afterglow Maverick Sabre, also known as Ricky, is a black Standard Poodle show <span class=\"searchmatch\">dog</span> owned at that time by his handler Jason Lynn together with John and Sandra",
    "timestamp": "2018-04-18T13:23:35Z"
  },
  {
    "ns": 0,
    "title": "List of dog diseases",
    "pageid": 3858681,
    "size": 132025,
    "wordcount": 14331,
    "snippet": "This list of <span class=\"searchmatch\">dog</span> diseases is a selection of diseases and other conditions found in the <span class=\"searchmatch\">dog</span>. Some of these diseases are unique to dogs or closely related",
    "timestamp": "2018-09-01T08:59:36Z"
  },
  {
    "ns": 0,
    "title": "Families of Archie's Gang",
    "pageid": 26234889,
    "size": 40957,
    "wordcount": 6227,
    "snippet": "and Nathalie Boltt, respectively. Sugar is Cheryl Blossom\u2019s purebred <span class=\"searchmatch\">Pomeranian</span> <span class=\"searchmatch\">dog</span>. Although Cheryl may seem snobby and antagonistic at times, Sugar proves",
    "timestamp": "2018-10-26T10:48:40Z"
  },
  {
    "ns": 0,
    "title": "Fatal dog attacks in the United States",
    "pageid": 24807696,
    "size": 435274,
    "wordcount": 19625,
    "snippet": "million Americans are bitten by dogs every year, <span class=\"searchmatch\">dog</span> bites can cause pain, injury and infection. About 1 in 5 <span class=\"searchmatch\">dog</span> bites require medical attention. According",
    "timestamp": "2018-10-22T22:07:32Z"
  },
  {
    "ns": 0,
    "title": "List of dog breeds recognized by the Canadian Kennel Club",
    "pageid": 11087753,
    "size": 10221,
    "wordcount": 1052,
    "snippet": "A list of the <span class=\"searchmatch\">dog</span> breeds fully recognised by the Canadian Kennel Club. The list is organised by breed name, with the group name following, and the group's",
    "timestamp": "2018-09-16T02:31:16Z"
  },
  {
    "ns": 0,
    "title": "The Tale of the Pie and the Patty-Pan",
    "pageid": 4535237,
    "size": 24784,
    "wordcount": 3599,
    "snippet": "produced. Ribby was modelled on a cat living in Sawrey, Duchess on two <span class=\"searchmatch\">Pomeranians</span> belonging to Potter's neighbour Mrs Rogerson, Tabitha Twitchit on Potter's",
    "timestamp": "2018-10-13T12:05:56Z"
  },
  {
    "ns": 0,
    "title": "Guard goose",
    "pageid": 54023742,
    "size": 7847,
    "wordcount": 781,
    "snippet": "sources list the African goose, Roman goose (Tufted Roman), <span class=\"searchmatch\">Pomeranian</span> goose (Saddleback <span class=\"searchmatch\">Pomeranian</span>), and Chinese goose as the best breeds for guard duty.",
    "timestamp": "2018-06-20T20:05:17Z"
  },
  {
    "ns": 0,
    "title": "List of individual dogs",
    "pageid": 187637,
    "size": 133216,
    "wordcount": 15072,
    "snippet": "completely. After Lombard's death in 1942, the <span class=\"searchmatch\">dog</span> would not leave Gable's side. Giggy, a <span class=\"searchmatch\">Pomeranian</span> belonging to London born Beverly Hills business",
    "timestamp": "2018-10-23T05:17:26Z"
  },
  {
    "ns": 0,
    "title": "Alopekis",
    "pageid": 41162210,
    "size": 19000,
    "wordcount": 2344,
    "snippet": "\u2013 archaic <span class=\"searchmatch\">dog</span> type, ancestral / archetypical to the subsequent central European small Spitz/ Nordic and Terrier breeds. The <span class=\"searchmatch\">Pomeranian</span> <span class=\"searchmatch\">dog</span>, said to be",
    "timestamp": "2018-10-13T13:10:10Z"
  },
  {
    "ns": 0,
    "title": "San-X",
    "pageid": 2205903,
    "size": 23574,
    "wordcount": 2550,
    "snippet": "- A hedgehog <span class=\"searchmatch\">dog</span>. Harinezutan - a fashion-conscious hedgehog character, launched in February 2003. Homekoro - a round, brown <span class=\"searchmatch\">Pomeranian</span>. Hoshikuma - A",
    "timestamp": "2018-09-18T20:06:10Z"
  },
  {
    "ns": 0,
    "title": "Gidget (disambiguation)",
    "pageid": 23553080,
    "size": 1181,
    "wordcount": 142,
    "snippet": " Gidget, a simplified interface to linux inotify, written in C. Gidget, a white <span class=\"searchmatch\">Pomeranian</span> character in the animated feature The Secret Life of Pets.",
    "timestamp": "2017-02-03T03:55:21Z"
  },
  {
    "ns": 0,
    "title": "Welcome Home Roscoe Jenkins",
    "pageid": 12695008,
    "size": 10174,
    "wordcount": 1290,
    "snippet": "<span class=\"searchmatch\">Pomeranian</span> Fifi, who had turned against Bianca and joined the Jenkins clan to pursue a relationship with the family's over-aged <span class=\"searchmatch\">dog</span>, Bucky (25 in <span class=\"searchmatch\">dog</span>",
    "timestamp": "2018-10-30T06:35:39Z"
  },
  {
    "ns": 0,
    "title": "On the Air (TV series)",
    "pageid": 1579562,
    "size": 20805,
    "wordcount": 2076,
    "snippet": "him <span class=\"searchmatch\">dog</span> food, trades personalities with McGonigle, eats a wire attached to an important prop while it is in use, falls in love with a <span class=\"searchmatch\">Pomeranian</span> that",
    "timestamp": "2018-10-30T10:56:09Z"
  },
  {
    "ns": 0,
    "title": "List of adjectivals and demonyms for former regions",
    "pageid": 5436277,
    "size": 7025,
    "wordcount": 414,
    "snippet": "additional words is optional.) Notable examples are cheeses, cat breeds, <span class=\"searchmatch\">dog</span> breeds, and horse breeds. (See List of words derived from toponyms.) Where",
    "timestamp": "2018-05-28T18:20:17Z"
  },
  {
    "ns": 0,
    "title": "Gebhard Leberecht von Bl\u00fccher",
    "pageid": 178312,
    "size": 35961,
    "wordcount": 4128,
    "snippet": "the Swedish Army. He was captured by the Prussians in 1760 during the <span class=\"searchmatch\">Pomeranian</span> Campaign and thereafter joined the Prussian Army, serving as a hussar",
    "timestamp": "2018-10-28T10:55:10Z"
  },
  {
    "ns": 0,
    "title": "Natural regions of Germany",
    "pageid": 23350794,
    "size": 32244,
    "wordcount": 2804,
    "snippet": "Marsh (D24) 68 Schleswig-Holstein Marsh (D21) 71 Mecklenburg-Western <span class=\"searchmatch\">Pomeranian</span> Littoral (D01) 70 Schleswig-Holstein Uplands (D23) Northeast Mecklenburg",
    "timestamp": "2018-06-03T15:54:22Z"
  },
  {
    "ns": 0,
    "title": "Rob Dyrdek",
    "pageid": 11889949,
    "size": 28427,
    "wordcount": 2594,
    "snippet": "Fantasy Factory. He also has two bulldogs named Meaty and Beefy, and <span class=\"searchmatch\">Pomeranian</span> <span class=\"searchmatch\">dog</span> named Gretchen Weiner. Dyrdek became an ordained minister through the",
    "timestamp": "2018-10-12T22:50:06Z"
  },
  {
    "ns": 0,
    "title": "Hold That Kiss",
    "pageid": 24806261,
    "size": 4219,
    "wordcount": 475,
    "snippet": "the Westminster <span class=\"searchmatch\">Dog</span> Show, where they run into Piermont again. He has two dogs entered in the competition. Piermont insists his <span class=\"searchmatch\">Pomeranian</span> will win, but",
    "timestamp": "2018-09-23T01:33:57Z"
  },
  {
    "ns": 0,
    "title": "Second Polish Republic",
    "pageid": 14245,
    "size": 75276,
    "wordcount": 6649,
    "snippet": "Polish Eastern Provinces (London: Hollis &amp; Carter 1950) Eva Plach, &quot;Dogs and <span class=\"searchmatch\">dog</span> breeding in interwar Poland,&quot; Canadian Slavonic Papers 60. no 3-4 Small Statistical",
    "timestamp": "2018-10-29T11:44:47Z"
  },
  {
    "ns": 0,
    "title": "R. M. Koster",
    "pageid": 9577575,
    "size": 8176,
    "wordcount": 1133,
    "snippet": "of his soul ensues when he acquires an unlikely champion: a faithful <span class=\"searchmatch\">Pomeranian</span> <span class=\"searchmatch\">dog</span>, who instinctively knows something is up, and what to do about it. John",
    "timestamp": "2018-10-12T02:11:54Z"
  },
  {
    "ns": 0,
    "title": "List of Maison Ikkoku characters",
    "pageid": 11615419,
    "size": 34085,
    "wordcount": 5254,
    "snippet": "is pregnant, while in fact Salade (Asuna's own <span class=\"searchmatch\">pomeranian</span>) is. Salade (\u30b5\u30e9\u30c0, Sarada) is Asuna's <span class=\"searchmatch\">Pomeranian</span>, one of her many pet dogs. Salade later gives",
    "timestamp": "2018-08-28T18:15:56Z"
  },
  {
    "ns": 0,
    "title": "Doglands",
    "pageid": 36245093,
    "size": 17895,
    "wordcount": 2620,
    "snippet": "going to get neutered. Milly, Molly, Mandy, etc. are eight female dogs: a <span class=\"searchmatch\">Pomeranian</span>, a cockapoo, a Miniature Schnauzer, a Jack Russell Terrier, a Cavalier",
    "timestamp": "2018-10-13T10:51:09Z"
  },
  {
    "ns": 0,
    "title": "List of cultural icons of Germany",
    "pageid": 19958682,
    "size": 13768,
    "wordcount": 915,
    "snippet": "independently considered to be cultural icons characteristic of Germany. [1]. Boxer (<span class=\"searchmatch\">dog</span>) Dachshund German Shepherd Poodle Schnauzer Reinhold Begas (1831-1911) Otto",
    "timestamp": "2018-10-11T01:49:01Z"
  },
  {
    "ns": 0,
    "title": "2015 Kids' Choice Awards",
    "pageid": 42375597,
    "size": 26128,
    "wordcount": 956,
    "snippet": "Sheppard Lorde Jamie McDell Iggy Azalea Grumpy Cat Dr. Colosso Boo the <span class=\"searchmatch\">Pomeranian</span> Meredith Grey and Olivia Benson Munchkin the Teddy Bear KATY CATS 5SOSFAM",
    "timestamp": "2018-09-18T08:24:32Z"
  },
  {
    "ns": 0,
    "title": "List of adjectival and demonymic forms of place names",
    "pageid": 244356,
    "size": 32510,
    "wordcount": 508,
    "snippet": "additional words is optional.) Notable examples are cheeses, cat breeds, <span class=\"searchmatch\">dog</span> breeds, and horse breeds. (See List of words derived from toponyms.) Entries",
    "timestamp": "2018-10-23T16:56:51Z"
  },
  {
    "ns": 0,
    "title": "Cheryl Blossom",
    "pageid": 207929,
    "size": 13730,
    "wordcount": 1617,
    "snippet": "eponymous series, Cheryl can be kind and caring. She cares for her <span class=\"searchmatch\">dog</span>, a <span class=\"searchmatch\">Pomeranian</span> named Sugar, and rescues animals in need. In stories featuring Betty",
    "timestamp": "2018-10-25T08:18:18Z"
  },
  {
    "ns": 0,
    "title": "List of recurring characters in The Suite Life of Zack & Cody",
    "pageid": 6950967,
    "size": 49281,
    "wordcount": 6949,
    "snippet": "London's spoiled <span class=\"searchmatch\">dog</span>. She is a <span class=\"searchmatch\">Pomeranian</span>, and appears to be a lot smarter than London. In the episode &quot;Crushed&quot;, she and Scamp, Maddie's <span class=\"searchmatch\">dog</span>, fall in love",
    "timestamp": "2018-10-20T16:14:31Z"
  },
  {
    "ns": 0,
    "title": "Tokyo Jungle",
    "pageid": 28671589,
    "size": 20990,
    "wordcount": 2169,
    "snippet": "Australian Silky Terrier, a Smilodon, a robot <span class=\"searchmatch\">dog</span>, a Peking Man, a (human) office worker, white and black <span class=\"searchmatch\">Pomeranians</span>, a cat, a panda, a crocodile, a kangaroo",
    "timestamp": "2018-07-03T18:02:56Z"
  },
  {
    "ns": 0,
    "title": "List of bog bodies",
    "pageid": 30229848,
    "size": 79005,
    "wordcount": 2609,
    "snippet": "Rosendahl, Wilfried, Markus Bertling, and Heather Gill-Frerking. &quot;The Bog <span class=\"searchmatch\">Dog</span> From Burlage.&quot; Mummies of the World. Ed. Alfried Wieczorek and Wilfried Rosendahl",
    "timestamp": "2018-06-17T11:12:22Z"
  },
  {
    "ns": 0,
    "title": "List of Balto characters",
    "pageid": 20143457,
    "size": 50147,
    "wordcount": 7857,
    "snippet": "Peter MacNicol. Dixie and Sylvie are a pair of female <span class=\"searchmatch\">dog</span> gossipers in Balto. Dixie is a <span class=\"searchmatch\">Pomeranian</span> and Sylvie is an Afghan Hound. Both appear to be good",
    "timestamp": "2018-10-08T12:51:57Z"
  },
  {
    "ns": 0,
    "title": "Sonoma Academy",
    "pageid": 1907827,
    "size": 4726,
    "wordcount": 471,
    "snippet": "emotional therapy <span class=\"searchmatch\">dog</span>; Josie, a yellow labrador retriever; Bento, a fawn pug; Jojo, a mixed-breed terrier; Freckles, a <span class=\"searchmatch\">Pomeranian</span>; Maggie, a goldendoodle;",
    "timestamp": "2018-02-21T16:54:40Z"
  },
  {
    "ns": 0,
    "title": "Gesellschaft zur Erhaltung alter und gef\u00e4hrdeter Haustierrassen",
    "pageid": 43581700,
    "size": 10415,
    "wordcount": 640,
    "snippet": "1994\u00a0(1994): Westphalian (chicken) 1994\u00a0(1994): Diepholzer (goose) 1994\u00a0(1994): <span class=\"searchmatch\">Pomeranian</span> duck 1995\u00a0(1995): Bentheim Black Pied (pig) 1996\u00a0(1996): Schleswig Coldblood",
    "timestamp": "2017-12-17T11:50:50Z"
  },
  {
    "ns": 0,
    "title": "Wies\u0142aw Adamski",
    "pageid": 25211175,
    "size": 19167,
    "wordcount": 2453,
    "snippet": "Szczecinek, state emblem - an eagle on the monument commemorating the <span class=\"searchmatch\">Pomeranian</span> Emblem Winners, bas-relief of an eagle on the building of the Szczecin",
    "timestamp": "2018-09-26T18:25:28Z"
  },
  {
    "ns": 0,
    "title": "Dogs in the American Revolutionary War",
    "pageid": 52014686,
    "size": 12542,
    "wordcount": 1543,
    "snippet": "he went. He is remembered for his eccentric love of dogs and for his <span class=\"searchmatch\">Pomeranian</span>, Spado (sometimes referred to as Spada). Lee wrote to George Washington",
    "timestamp": "2018-10-07T01:51:36Z"
  },
  {
    "ns": 0,
    "title": "Cryptorchidism",
    "pageid": 415293,
    "size": 34290,
    "wordcount": 4381,
    "snippet": "Chihuahua Dachshund (miniature) Bulldog Maltese Miniature Schnauzer Pekingese <span class=\"searchmatch\">Pomeranian</span> Poodle (toy and miniature) Pug Shetland Sheepdog Siberian Husky Whippet",
    "timestamp": "2018-09-16T20:00:28Z"
  },
  {
    "ns": 0,
    "title": "Ajay Rochester",
    "pageid": 4171252,
    "size": 11896,
    "wordcount": 1406,
    "snippet": "Rochester appeared on the reality television series Celebrity <span class=\"searchmatch\">Dog</span> School with her <span class=\"searchmatch\">Pomeranian</span>, &quot;Bootsie&quot;. Rochester was also the co-host of the SBS TV series",
    "timestamp": "2018-10-21T11:19:39Z"
  },
  {
    "ns": 0,
    "title": "Solatorobo: Red the Hunter",
    "pageid": 26604149,
    "size": 27228,
    "wordcount": 2925,
    "snippet": "sister Chocolat Gelato (Voiced by Kana Asumi), a mechanically-minded <span class=\"searchmatch\">Pomeranian</span> Caninu who supports him over Dahak's com system. Much of the story revolves",
    "timestamp": "2018-10-30T18:37:35Z"
  },
  {
    "ns": 0,
    "title": "Pommern (disambiguation)",
    "pageid": 24416,
    "size": 776,
    "wordcount": 101,
    "snippet": "Swedish Pomerania, a Dominion under the Swedish Crown from 1630 to 1815, situated on what is now the Baltic coast of Germany and Poland <span class=\"searchmatch\">Pomeranian</span> (<span class=\"searchmatch\">dog</span>)",
    "timestamp": "2016-02-13T21:13:36Z"
  },
  {
    "ns": 0,
    "title": "Griffin",
    "pageid": 7713110,
    "size": 37513,
    "wordcount": 4399,
    "snippet": "of the dukes of Pomerania and survives today as the armorial of West <span class=\"searchmatch\">Pomeranian</span> Voivodeship (historically, Farther Pomerania) in Poland. It is also part",
    "timestamp": "2018-10-20T15:21:09Z"
  },
  {
    "ns": 0,
    "title": "List of adjectivals and demonyms for subcontinental regions",
    "pageid": 5632643,
    "size": 15099,
    "wordcount": 411,
    "snippet": "additional words is optional.) Notable examples are cheeses, cat breeds, <span class=\"searchmatch\">dog</span> breeds, and horse breeds. (See List of words derived from toponyms.) Where",
    "timestamp": "2018-05-04T16:23:07Z"
  },
  {
    "ns": 0,
    "title": "List of Too Cute episodes",
    "pageid": 53162361,
    "size": 33933,
    "wordcount": 59,
    "snippet": "\u00a02013\u00a0(2013-03-16) Lab mix rescue pup Sally is never seen far behind brother Safari, <span class=\"searchmatch\">Pomeranian</span> triplets Sparrow, Wren and Finch carry on mom Star and dad Tucker's job",
    "timestamp": "2018-10-02T07:59:12Z"
  },
  {
    "ns": 0,
    "title": "Girl Shy",
    "pageid": 3371111,
    "size": 8560,
    "wordcount": 1064,
    "snippet": "aboard, so she hides her <span class=\"searchmatch\">Pomeranian</span> under her shawl, but her pet jumps off as the train pulls away. Harold rescues her <span class=\"searchmatch\">dog</span> and helps Mary hide it from",
    "timestamp": "2018-06-11T23:13:54Z"
  },
  {
    "ns": 0,
    "title": "Characters in Ghost Trick: Phantom Detective",
    "pageid": 30880157,
    "size": 46861,
    "wordcount": 6485,
    "snippet": "accused of murdering his wife; Kamila, the daughter of Jowd; Missile, a <span class=\"searchmatch\">Pomeranian</span> who, after dying, chooses to stay dead so that he can protect his owner",
    "timestamp": "2018-07-22T15:57:20Z"
  },
  {
    "ns": 0,
    "title": "In a Good Way",
    "pageid": 42407989,
    "size": 23594,
    "wordcount": 2426,
    "snippet": " but as she's about to walk away a <span class=\"searchmatch\">Pomeranian</span> <span class=\"searchmatch\">dog</span> runs her way chasing after the basketball. Jia En sees the <span class=\"searchmatch\">dog</span> and pets him. When the dogs owner comes",
    "timestamp": "2018-10-20T08:02:37Z"
  },
  {
    "ns": 0,
    "title": "German language",
    "pageid": 11884,
    "size": 147231,
    "wordcount": 14822,
    "snippet": "to the constitutional amendment number 11/2009 establishing the East <span class=\"searchmatch\">Pomeranian</span> dialect as well as German as cultural heritage of the state&quot; (PDF). Claudiovereza",
    "timestamp": "2018-10-28T14:47:53Z"
  },
  {
    "ns": 0,
    "title": "Canine gallbladder mucocele",
    "pageid": 58203983,
    "size": 12577,
    "wordcount": 1453,
    "snippet": "dogs. Smaller dogs including Cocker Spaniels, Miniature Schnauzers, <span class=\"searchmatch\">Pomeranians</span> and Shetland Sheepdogs are also predisposed to developing gallbladder",
    "timestamp": "2018-10-24T21:37:31Z"
  },
  {
    "ns": 0,
    "title": "Ni una Sola Palabra",
    "pageid": 6183431,
    "size": 7958,
    "wordcount": 590,
    "snippet": "first music video (since 2001's &quot;Yo No Soy Esa Mujer&quot;) to feature her <span class=\"searchmatch\">Pomeranian</span> <span class=\"searchmatch\">dog</span>, Miranda. The music video was released on Latin music video stations",
    "timestamp": "2018-06-29T21:17:41Z"
  },
  {
    "ns": 0,
    "title": "Lincoln Park, Chicago",
    "pageid": 421987,
    "size": 37757,
    "wordcount": 3383,
    "snippet": "The current Romanesque Revival church building was completed in 1902. A <span class=\"searchmatch\">Pomeranian</span> Griffin Crest visible on the school south of the church is a nod to the",
    "timestamp": "2018-10-01T20:45:00Z"
  },
  {
    "ns": 0,
    "title": "List of Dave and Morley stories",
    "pageid": 7005651,
    "size": 22779,
    "wordcount": 3513,
    "snippet": "Dave thinks that Mary is stiff and intimidating.'They have a teacup <span class=\"searchmatch\">Pomeranian</span> <span class=\"searchmatch\">dog</span> named Tissue. Ted and Polly Anderson are an elegant upper-class couple",
    "timestamp": "2018-10-19T16:16:22Z"
  },
  {
    "ns": 0,
    "title": "Louis Untermeyer",
    "pageid": 734724,
    "size": 17394,
    "wordcount": 1939,
    "snippet": "Victor The World's Great Stories (1964) The Firebringer (1968) Lines to a <span class=\"searchmatch\">Pomeranian</span> Puppy Valued at $3500 (1950), musical adaptation of Untermeyer poem by",
    "timestamp": "2018-10-14T06:07:15Z"
  },
  {
    "ns": 0,
    "title": "Littlest Pet Shop: A World of Our Own",
    "pageid": 56767410,
    "size": 43787,
    "wordcount": 1659,
    "snippet": "of the series. Sweetie Pom-Pom (voiced by Brittney Wilson) is a yellow <span class=\"searchmatch\">pomeranian</span> and one of Petula\u2019s sidekicks. Gavin Chamelle (voiced by Alessandro Juliani)",
    "timestamp": "2018-10-28T10:33:34Z"
  },
  {
    "ns": 0,
    "title": "Kashmakash (1973 film)",
    "pageid": 44112049,
    "size": 5441,
    "wordcount": 664,
    "snippet": "illicit dealings to blackmail them. He always carries his pet white <span class=\"searchmatch\">Pomeranian</span> <span class=\"searchmatch\">dog</span> with him as his signature at the places he investigates along with the",
    "timestamp": "2018-06-19T14:40:55Z"
  },
  {
    "ns": 0,
    "title": "Lifeboats of the RMS Titanic",
    "pageid": 35186399,
    "size": 90045,
    "wordcount": 12623,
    "snippet": "Elizabeth Rothschild had her <span class=\"searchmatch\">Pomeranian</span> with her in the lifeboat. Initially, crew members of the Carpathia refused to take the <span class=\"searchmatch\">dog</span> aboard, but Mrs. Rothschild",
    "timestamp": "2018-10-30T06:54:00Z"
  },
  {
    "ns": 0,
    "title": "Slavomolisano dialect",
    "pageid": 1317401,
    "size": 25448,
    "wordcount": 2582,
    "snippet": "the fox placed a <span class=\"searchmatch\">dog</span> under the weighing pan. Now the fox said to the lark: &quot;Take the weighing pan!&quot;; the lark took the pan, the <span class=\"searchmatch\">dog</span> came out, he began",
    "timestamp": "2018-05-28T09:30:51Z"
  },
  {
    "ns": 0,
    "title": "Poland in antiquity",
    "pageid": 13986375,
    "size": 72202,
    "wordcount": 9867,
    "snippet": "several enclaves mostly in the southern part of the country, within the <span class=\"searchmatch\">Pomeranian</span> or Lusatian populations or in areas abandoned by those people. The cultures",
    "timestamp": "2018-10-22T15:57:39Z"
  },
  {
    "ns": 0,
    "title": "The Supervet",
    "pageid": 44776817,
    "size": 63905,
    "wordcount": 635,
    "snippet": "'on the road,' mixing up the traditional format, with visits to various <span class=\"searchmatch\">dog</span> shows and other types of pets in the community. NOTE: Series 4 was a spin-off",
    "timestamp": "2018-10-26T19:52:18Z"
  },
  {
    "ns": 0,
    "title": "List of pirates",
    "pageid": 1368051,
    "size": 160843,
    "wordcount": 3698,
    "snippet": "Travel and Exploration: An Encyclopedia, volume 1. Walling, R.A.J. A Sea-<span class=\"searchmatch\">Dog</span> of Devon: a Life of Sir John Hawkins. 1907. Williamson, James. Hawkins of",
    "timestamp": "2018-10-23T17:15:29Z"
  },
  {
    "ns": 0,
    "title": "List of Littlest Pet Shop (2012 TV series) characters",
    "pageid": 40701730,
    "size": 48528,
    "wordcount": 6662,
    "snippet": "who appears in &quot;Game of Groans&quot;. A female <span class=\"searchmatch\">Pomeranian</span> with blue eyes. Snobby and narcissistic, she won a <span class=\"searchmatch\">dog</span> modelling show against Zoe, starting a rivalry",
    "timestamp": "2018-10-04T21:07:41Z"
  },
  {
    "ns": 0,
    "title": "Deities of Slavic religion",
    "pageid": 14385824,
    "size": 97364,
    "wordcount": 2579,
    "snippet": " ISBN\u00a09788373182059. Trkanjec, Luka (2013). &quot;Chthonic aspects of the <span class=\"searchmatch\">Pomeranian</span> deity Triglav and other tricephalic characters in Slavic mythology&quot; (PDF)",
    "timestamp": "2018-10-27T17:27:30Z"
  },
  {
    "ns": 0,
    "title": "The Suite Life on Deck",
    "pageid": 15627191,
    "size": 53035,
    "wordcount": 5121,
    "snippet": "can't remember the difference between Zack and Cody). She also has a <span class=\"searchmatch\">pomeranian</span> pet <span class=\"searchmatch\">dog</span> named Ivana. When she is happy, she usually claps her hands and repeatedly",
    "timestamp": "2018-10-25T06:34:13Z"
  },
  {
    "ns": 0,
    "title": "B\u00e9la II of Hungary",
    "pageid": 2299066,
    "size": 23764,
    "wordcount": 2402,
    "snippet": "purpose, he gave financial support to Otto of Bamberg's missions among the <span class=\"searchmatch\">Pomeranians</span> and arranged the engagement of his daughter Sophia with Henry, son of",
    "timestamp": "2018-08-19T23:10:23Z"
  },
  {
    "ns": 0,
    "title": "List of dog breeds recognized by the FCI",
    "pageid": 42784559,
    "size": 92145,
    "wordcount": 712,
    "snippet": "Spanish FCI name. List of <span class=\"searchmatch\">dog</span> breeds for full list of all <span class=\"searchmatch\">dog</span> breeds, including those not recognised by the FCI. List of <span class=\"searchmatch\">dog</span> breeds recognized by the American",
    "timestamp": "2018-10-13T12:46:35Z"
  },
  {
    "ns": 0,
    "title": "Christian Thomsen Carl",
    "pageid": 38442749,
    "size": 45517,
    "wordcount": 5251,
    "snippet": "Ditmarsken and was put in charge of vice-admiral Christen Thomesen Sehested's <span class=\"searchmatch\">Pomeranian</span> fleet during his absence. Carl took part in the action of 21\u201323 June 1712",
    "timestamp": "2018-09-26T15:06:49Z"
  },
  {
    "ns": 0,
    "title": "Anything Goes",
    "pageid": 393674,
    "size": 57311,
    "wordcount": 4960,
    "snippet": "jacket taken from a drunken passenger, and hair cut from Mrs. Harcourt's <span class=\"searchmatch\">Pomeranian</span> and made into a beard. Reno tells Billy that Evelyn has kissed her, and",
    "timestamp": "2018-09-14T14:58:18Z"
  },
  {
    "ns": 0,
    "title": "List of Can I Pet Your Dog? episodes",
    "pageid": 48311450,
    "size": 41448,
    "wordcount": 2083,
    "snippet": "This is a list of Can I Pet Your <span class=\"searchmatch\">Dog</span>? episodes produced and distributed by Maximum Fun and hosted by Allegra Ringo, Renee Colvert, current producer Alexis",
    "timestamp": "2018-08-01T04:15:13Z"
  },
  {
    "ns": 0,
    "title": "List of long place names",
    "pageid": 22171108,
    "size": 34767,
    "wordcount": 3355,
    "snippet": "Full name: Brzyskorzystewko (16 letters) Location: \u017bnin County, Kuyavian-<span class=\"searchmatch\">Pomeranian</span> Voivodeship, Poland Language: Polish Translation: Unknown Full name: Penrhyndeudraeth",
    "timestamp": "2018-10-14T17:11:45Z"
  },
  {
    "ns": 0,
    "title": "Bombing of Dresden in World War II",
    "pageid": 64692,
    "size": 107881,
    "wordcount": 12820,
    "snippet": "Bismarck: &quot;The whole of the Balkans is not worth the bones of a single <span class=\"searchmatch\">Pomeranian</span> grenadier&quot;. Under pressure from the Chiefs of Staff and in response to",
    "timestamp": "2018-10-26T01:45:17Z"
  },
  {
    "ns": 0,
    "title": "Swansea",
    "pageid": 46394,
    "size": 106260,
    "wordcount": 10769,
    "snippet": "Pyr\u00e9n\u00e9es-Atlantiques, Nouvelle-Aquitaine, France Bydgoszcz, Kuyavian-<span class=\"searchmatch\">Pomeranian</span> Voivodeship, Poland. It also has a friendship link with Nantong, China",
    "timestamp": "2018-10-14T20:14:31Z"
  },
  {
    "ns": 0,
    "title": "List of fictional countries by region",
    "pageid": 11089708,
    "size": 18335,
    "wordcount": 2210,
    "snippet": "a nation in the film Anchors Aweigh. It has a navy which accepts non-<span class=\"searchmatch\">Pomeranians</span>. Not to be confused with the real Pomerania, formerly a region of Prussia",
    "timestamp": "2018-08-06T13:52:35Z"
  },
  {
    "ns": 0,
    "title": "Baltic Fleet",
    "pageid": 1634766,
    "size": 47400,
    "wordcount": 4531,
    "snippet": "Years' War&quot;, (1755-1763), the Russian Baltic Sea fleet was active on the <span class=\"searchmatch\">Pomeranian</span> coast of northern Germany and Prussia, helping the infantry to take Memel",
    "timestamp": "2018-10-18T12:00:05Z"
  },
  {
    "ns": 0,
    "title": "Judith Blunt-Lytton, 16th Baroness Wentworth",
    "pageid": 7280574,
    "size": 8942,
    "wordcount": 976,
    "snippet": "the history and management of Toy Spaniels, Pekingese, Japanese and <span class=\"searchmatch\">Pomeranians</span>&quot; Duckworth &amp; Co., 1911. Lytton, Lady Anne. &quot;Memories of Crabbet Stud",
    "timestamp": "2018-05-29T09:30:06Z"
  },
  {
    "ns": 0,
    "title": "Otto von Bismarck",
    "pageid": 22416,
    "size": 143552,
    "wordcount": 17455,
    "snippet": "our risking\u2014excuse my plain speaking\u2014the healthy bones of one of our <span class=\"searchmatch\">Pomeranian</span> musketeers.&quot; A leading diplomatic historian of the era, William L. Langer",
    "timestamp": "2018-10-26T00:37:34Z"
  },
  {
    "ns": 0,
    "title": "Dance with Devils",
    "pageid": 47432176,
    "size": 35428,
    "wordcount": 1383,
    "snippet": "R\u014den) Voiced by: Kazutomi Yamamoto (<span class=\"searchmatch\">dog</span>), Tatsuhisa Suzuki (human) (Japanese); Derick Snow (English) Rem's pet <span class=\"searchmatch\">Pomeranian</span>. He is terrified of Shiki due to",
    "timestamp": "2018-09-02T06:34:39Z"
  },
  {
    "ns": 0,
    "title": "Erix Logan",
    "pageid": 51237078,
    "size": 7469,
    "wordcount": 801,
    "snippet": "Italian law. They have no children but a <span class=\"searchmatch\">dog</span> which is an integral part of their family. He is a <span class=\"searchmatch\">Pomeranian</span> named Bartolo.  Impaled (illusion)     Silvan",
    "timestamp": "2018-02-27T07:46:07Z"
  },
  {
    "ns": 0,
    "title": "Yamada-kun and the Seven Witches",
    "pageid": 40318182,
    "size": 36561,
    "wordcount": 2301,
    "snippet": "telepathy. They can hear Otsuka's thoughts as well as that of her <span class=\"searchmatch\">dog</span>, who is a <span class=\"searchmatch\">pomeranian</span> that's been styled to look like a shiba inu. Otsuka tells the gang",
    "timestamp": "2018-10-23T07:37:05Z"
  },
  {
    "ns": 0,
    "title": "Dorothy Levitt",
    "pageid": 8428887,
    "size": 42871,
    "wordcount": 4979,
    "snippet": "at Monte Carlo.&quot; Levitt was noted for her ever-present, yappy, black <span class=\"searchmatch\">Pomeranian</span> <span class=\"searchmatch\">dog</span> called Dodo. A gift from Mademoiselle Marie Cornelle around 1903, he",
    "timestamp": "2018-05-22T00:50:22Z"
  },
  {
    "ns": 0,
    "title": "List of minor Blandings characters",
    "pageid": 4626533,
    "size": 86061,
    "wordcount": 12076,
    "snippet": "(at one point she owns four Pekes (one of which is called Susan), two <span class=\"searchmatch\">Pomeranians</span>, a Yorkshire Terrier, five Sealyhams, a Borzoi and an Airedale), making",
    "timestamp": "2018-10-15T03:17:53Z"
  },
  {
    "ns": 0,
    "title": "Dog coat genetics",
    "pageid": 54484922,
    "size": 56128,
    "wordcount": 6794,
    "snippet": "Modern breeds of <span class=\"searchmatch\">dog</span> exhibit a diverse range of coat colorings, patterns, lengths and textures. In recent years, the understanding of the genetic basis",
    "timestamp": "2018-08-13T17:28:55Z"
  },
  {
    "ns": 0,
    "title": "The Real Housewives of Melbourne (season 2)",
    "pageid": 51399414,
    "size": 41463,
    "wordcount": 2738,
    "snippet": "for jogs, getting botox, designing her handbag range, and spoiling her <span class=\"searchmatch\">Pomeranians</span>, Cash and Wicket. Berenger is a Sri Lanken born property developer who",
    "timestamp": "2018-01-06T20:54:35Z"
  },
  {
    "ns": 0,
    "title": "Midsummer",
    "pageid": 221226,
    "size": 79684,
    "wordcount": 10445,
    "snippet": "dream of her future husband. Especially in northern Poland \u2013 the Eastern <span class=\"searchmatch\">Pomeranian</span> and Kashubian regions \u2013 midsummer is celebrated on June 23. People dress",
    "timestamp": "2018-10-24T19:27:33Z"
  },
  {
    "ns": 0,
    "title": "List of Underbelly: Razor episodes",
    "pageid": 32840547,
    "size": 11103,
    "wordcount": 171,
    "snippet": "Gawler21\u00a0August\u00a02011\u00a0(2011-08-21) In 1927, after Tilly Devine steals Kate Leigh's <span class=\"searchmatch\">Pomeranian</span> <span class=\"searchmatch\">dog</span> they become sworn enemies. Nellie Cameron and Frank Green join Tilly",
    "timestamp": "2017-09-03T21:11:26Z"
  },
  {
    "ns": 0,
    "title": "List of Archie Comics characters",
    "pageid": 808850,
    "size": 101019,
    "wordcount": 15142,
    "snippet": "want them to learn a little humility. Sugar Blossom: Cheryl's beloved <span class=\"searchmatch\">Pomeranian</span> <span class=\"searchmatch\">dog</span>. Bingo Wilkin: Jughead Jones's cousin. A rambunctious teenaged boy who",
    "timestamp": "2018-10-16T06:30:14Z"
  },
  {
    "ns": 0,
    "title": "List of The Rosie Show episodes",
    "pageid": 33395125,
    "size": 16853,
    "wordcount": 45,
    "snippet": "possible! From Molly Shannon's musical stylings to Fran Drescher's pampered <span class=\"searchmatch\">Pomeranian</span>, these funny women kept the audience in stitches. Plus, Jenny McCarthy",
    "timestamp": "2017-04-19T21:38:17Z"
  },
  {
    "ns": 0,
    "title": "Maeve Fort",
    "pageid": 19572449,
    "size": 8509,
    "wordcount": 858,
    "snippet": "accompanied by &quot;the boys&quot;, one of whom carried her beloved <span class=\"searchmatch\">dog</span>, Chloe, a white <span class=\"searchmatch\">Pomeranian</span>-Maltese cross, in a knapsack. Fort was appointed High Commissioner",
    "timestamp": "2018-06-26T13:24:12Z"
  },
  {
    "ns": 0,
    "title": "List of sister cities in Florida",
    "pageid": 12230057,
    "size": 111880,
    "wordcount": 5706,
    "snippet": "2006. Retrieved July 16, 2007. Herald Staff (June 24, 1991). &quot;It's A <span class=\"searchmatch\">Dog</span>-Eat-<span class=\"searchmatch\">Dog</span> World&quot;. Miami Herald. p.\u00a02B. Retrieved July 16, 2007. Sen.... After commissioners",
    "timestamp": "2018-10-09T17:56:10Z"
  },
  {
    "ns": 0,
    "title": "Hero: 108",
    "pageid": 24058921,
    "size": 130249,
    "wordcount": 21340,
    "snippet": "Tong - Yan Ching Sean Cullen - Flying Squirrel King Lisa Ann Beley - <span class=\"searchmatch\">Pomeranian</span> Queen An MMORPG based on the series had the players play as First Squad",
    "timestamp": "2018-10-28T05:26:03Z"
  },
  {
    "ns": 0,
    "title": "Pet policy in public housing estates in Hong Kong",
    "pageid": 55937596,
    "size": 74578,
    "wordcount": 7607,
    "snippet": "natural death of the <span class=\"searchmatch\">dog</span>. Nevertheless, estates under the Tenants Purchase Scheme were not benefited from the relaxation of rules about <span class=\"searchmatch\">dog</span> keeping, since these",
    "timestamp": "2018-07-15T10:45:56Z"
  },
  {
    "ns": 0,
    "title": "Jasper Liu",
    "pageid": 43944716,
    "size": 28231,
    "wordcount": 2914,
    "snippet": "breast cancer, his older sister suffered high blood pressure and his pet <span class=\"searchmatch\">Pomeranian</span> <span class=\"searchmatch\">dog</span> &quot;ChiChi&quot; that he'd raised for 17 years (and often referred to as his",
    "timestamp": "2018-10-21T19:21:21Z"
  },
  {
    "ns": 0,
    "title": "Horseland (TV series)",
    "pageid": 9113961,
    "size": 42963,
    "wordcount": 3410,
    "snippet": "concern whenever Shep and Teeny are in true danger. Cubby is a brown <span class=\"searchmatch\">Pomeranian</span> puppy. He was found abandoned by Bailey in &quot;New Pup in Town&quot;. Bailey later",
    "timestamp": "2018-09-28T14:14:43Z"
  },
  {
    "ns": 0,
    "title": "April 1945",
    "pageid": 1800650,
    "size": 43236,
    "wordcount": 4959,
    "snippet": "Sturmbannf\u00fchrer (killed during an Allied air raid on F\u00fcrstenfeld, Austria) The East <span class=\"searchmatch\">Pomeranian</span> Offensive ended in Soviet victory. The Battle of Kassel ended in Allied",
    "timestamp": "2018-10-14T03:28:52Z"
  },
  {
    "ns": 0,
    "title": "Lips Are Movin",
    "pageid": 44276758,
    "size": 44800,
    "wordcount": 3926,
    "snippet": "Japanese nail artist Mei Kawajiri; American dancer Chachi Gonzales; and <span class=\"searchmatch\">Pomeranian</span> <span class=\"searchmatch\">dog</span> Barkley the Pom. Andelman suggested showcasing behind-the-scenes events",
    "timestamp": "2018-10-19T08:25:38Z"
  },
  {
    "ns": 0,
    "title": "Rainbow Brite (1984 TV series)",
    "pageid": 58565682,
    "size": 33376,
    "wordcount": 4563,
    "snippet": "bejeweled golden headdress adorning her auburn hair. She often carries a <span class=\"searchmatch\">pomeranian</span>-sized diamond on a leash like a pet and employs many underlings to do",
    "timestamp": "2018-10-28T18:18:32Z"
  },
  {
    "ns": 0,
    "title": "Deaths in January 2016",
    "pageid": 48909948,
    "size": 175890,
    "wordcount": 12240,
    "snippet": "French actor. Zbigniew Zychowicz, 62, Polish politician, Marshal of West <span class=\"searchmatch\">Pomeranian</span> Voivodeship (1999\u20132000). Brahim Chergui, 94, Algerian militant. Patrick",
    "timestamp": "2018-10-11T12:09:02Z"
  },
  {
    "ns": 0,
    "title": "List of shipwrecks in April 1918",
    "pageid": 37432126,
    "size": 90558,
    "wordcount": 1570,
    "snippet": "October 2012. &quot;Ailsa Craig&quot;. Uboat.net. Retrieved 12 November 2012. &quot;<span class=\"searchmatch\">Pomeranian</span>&quot;. Uboat.net. Retrieved 30 December 2012. &quot;Rostov&quot;. Uboat.net. Retrieved",
    "timestamp": "2018-10-05T16:38:39Z"
  },
  {
    "ns": 0,
    "title": "The Grass Dancer",
    "pageid": 28274345,
    "size": 31286,
    "wordcount": 4931,
    "snippet": "same drunk driving accident that killed his father. Chuck Norris: A <span class=\"searchmatch\">Pomeranian</span> <span class=\"searchmatch\">dog</span> that belongs to Harley Wind Soldier. Chuck Norris attends events with",
    "timestamp": "2018-10-29T20:33:43Z"
  },
  {
    "ns": 0,
    "title": "History of the Slavic languages",
    "pageid": 1211682,
    "size": 61224,
    "wordcount": 7430,
    "snippet": "but without any lengthening, and the northwestern Lechitic languages (<span class=\"searchmatch\">Pomeranian</span>, Slovincian and Polabian) retained *or without any metathesis at all.",
    "timestamp": "2018-09-25T16:50:15Z"
  },
  {
    "ns": 0,
    "title": "List of Mighty Med episodes",
    "pageid": 42838969,
    "size": 77381,
    "wordcount": 1033,
    "snippet": "burgeoning medical skills at school when he performs CPR on Stefanie's <span class=\"searchmatch\">Pomeranian</span>, which quickly elevates his social status much to Kaz's chagrin. When",
    "timestamp": "2018-10-30T15:01:16Z"
  },
  {
    "ns": 0,
    "title": "Net metering in Arizona",
    "pageid": 51159857,
    "size": 10473,
    "wordcount": 1364,
    "snippet": "rooftop-panel leasing companies took out ads depicting Little as a <span class=\"searchmatch\">Pomeranian</span> &quot;lap <span class=\"searchmatch\">dog</span>&quot; to APS.&quot;After Forese and Little won and began their terms, they",
    "timestamp": "2018-03-10T18:01:47Z"
  },
  {
    "ns": 0,
    "title": "Remilitarization of the Rhineland",
    "pageid": 7734670,
    "size": 136159,
    "wordcount": 19812,
    "snippet": "Bismarck: &quot;The whole of the Balkans is not worth the bones of a single <span class=\"searchmatch\">Pomeranian</span> grenadier.&quot; Emmerson, p. 24. Schuker (1999), pp. 48\u201349. Bennett, Edward",
    "timestamp": "2018-10-01T17:31:57Z"
  },
  {
    "ns": 0,
    "title": "List of shipwrecks in 1816",
    "pageid": 39762933,
    "size": 323171,
    "wordcount": 2984,
    "snippet": "with the loss of all hands.Johannes \u00a0Russia The ship was wrecked on the <span class=\"searchmatch\">Pomeranian</span> coast. She was on a voyage from Pillau, Prussia to Stettin, Prussia.Mary",
    "timestamp": "2018-10-24T17:45:26Z"
  },
  {
    "ns": 0,
    "title": "Michael Counts",
    "pageid": 53475746,
    "size": 65010,
    "wordcount": 8620,
    "snippet": "in ghoulish green light delivering a string of non-sequiturs about a <span class=\"searchmatch\">Pomeranian</span> as the statue of the greyhound stood sentinel nearby. This was followed",
    "timestamp": "2018-06-27T12:07:09Z"
  },
  {
    "ns": 0,
    "title": "Kuuma Empire",
    "pageid": 15527849,
    "size": 28210,
    "wordcount": 4170,
    "snippet": "The monster's name is the Filipino onomatopoeia of a <span class=\"searchmatch\">dog</span>'s bark. Can itself disguise as a <span class=\"searchmatch\">Pomeranian</span> named &quot;Mighty&quot; which can bite victims so they get infected",
    "timestamp": "2017-06-11T03:41:41Z"
  }
]